Workbook

Sheet Actuals
A4: Statement of Profit & Loss (Consolidated) | H4: Balance Sheet (Consolidated)
A5: Particulars | B5: FY22A | C5: FY23A | D5: FY24A | E5: FY25A | F5: FY26A | H5: Particulars | I5: FY22A | J5: FY23A | K5: FY24A | L5: FY25A | M5: FY26A
A6: Revenue from operations | B6: 4935.57 | C6: 6040.55 | D6: 5040.83 | E6: 5553.96 | F6: 6812.9 | H6: Property, plant & equipment | I6: 2257.29 | J6: 3015.96 | K6: 3446.37 | L6: 3668.46 | M6: 3873.23
A7: Other income | B7: 13.58 | C7: 1.44 | D7: 20.73 | E7: 59.93 | F7: 48.38 | H7: Right-of-use assets | I7: 138.05 | J7: 133.43 | K7: 178.32 | L7: 189.14 | M7: 232.71
A8: Total income | B8: =SUM(B6:B7) -> 4949.15 | C8: =SUM(C6:C7) -> 6041.99 | D8: =SUM(D6:D7) -> 5061.56 | E8: =SUM(E6:E7) -> 5613.89 | F8: =SUM(F6:F7) -> 6861.28 | H8: Capital work-in-progress | I8: 813.22 | J8: 550.78 | K8: 422.84 | L8: 458.36 | M8: 773.28
A9: Cost of materials consumed | B9: 2269.13 | C9: 2596.57 | D9: 2422.38 | E9: 2428.55 | F9: 2794.34 | H9: Goodwill | I9: 246.3 | J9: 246.3 | K9: 246.3 | L9: 246.3 | M9: 246.3
A10: Purchase of traded goods | B10: 145.81 | C10: 155.71 | D10: 110.92 | E10: 105.36 | F10: 172.56 | H10: Other intangible assets | I10: 10.83 | J10: 12.93 | K10: 19.02 | L10: 19.32 | M10: 18.4
A11: Changes in inventories | B11: -221.17 | C11: 22.04 | D11: -100.88 | E11: -55.93 | F11: -271.44 | H11: Investments (non-current) | I11: 30.81 | J11: 49.9 | K11: 123.98 | L11: 233.26 | M11: 309.27
A12: Employee benefits expense | B12: 501.53 | C12: 580.64 | D12: 639.93 | E12: 719.52 | F12: 895.45 | H12: Other financial assets (NC) | I12: 60.27 | J12: 49.41 | K12: 47.38 | L12: 48.66 | M12: 44.26
A13: Other expenses | B13: 817.84 | C13: 1093.4 | D13: 1190.98 | E13: 1301.18 | F13: 1444.28 | H13: Income tax assets (net, NC) | I13: 6.77 | J13: 20.44 | K13: 2.97 | L13: 6.94 | M13: 2.44
A14: Total expenses | B14: =SUM(B9:B13) -> 3513.14 | C14: =SUM(C9:C13) -> 4448.36 | D14: =SUM(D9:D13) -> 4263.33 | E14: =SUM(E9:E13) -> 4498.68 | F14: =SUM(F9:F13) -> 5035.19 | H14: Other non-current assets | I14: 59.89 | J14: 119.57 | K14: 64.88 | L14: 132.81 | M14: 182.09
A15: EBITDA | B15: =B8-B14 -> 1436.01 | C15: =C8-C14 -> 1593.63 | D15: =D8-D14 -> 798.23 | E15: =E8-E14 -> 1115.21 | F15: =F8-F14 -> 1826.09 | H15: Total non-current assets | I15: =SUM(I6:I14) -> 3623.43 | J15: =SUM(J6:J14) -> 4198.72 | K15: =SUM(K6:K14) -> 4552.06 | L15: =SUM(L6:L14) -> 5003.25 | M15: =SUM(M6:M14) -> 5681.98
A16: Depreciation & amortisation | B16: 251.49 | C16: 324.08 | D16: 384.58 | E16: 430.09 | F16: 480.05 | H16: Inventories | I16: 1760.3 | J16: 1684.81 | K16: 1845.41 | L16: 1936.54 | M16: 2342.16
A17: Finance income | B17: -1.72 | C17: -4.56 | D17: -5.61 | E17: -15.17 | F17: -6.57 | H17: Trade receivables | I17: 1354.18 | J17: 1580.44 | K17: 1662.92 | L17: 2007.16 | M17: 2155.04
A18: Finance costs | B18: 102.39 | C18: 165.17 | D18: 182.9 | E18: 216 | F18: 170.73 | H18: Cash & cash equivalents | I18: 75.35 | J18: 45.67 | K18: 138.94 | L18: 99.54 | M18: 112.66
A19: Profit before tax (PBT) | B19: =B15-B16-B17-B18 -> 1083.85 | C19: =C15-C16-C17-C18 -> 1108.94 | D19: =D15-D16-D17-D18 -> 236.36 | E19: =E15-E16-E17-E18 -> 484.29 | F19: =F15-F16-F17-F18 -> 1181.88 | H19: Other bank balances | I19: 0.59 | J19: 2.79 | K19: 2.71 | L19: 44.67 | M19: 1.04
A20: Total tax expense | B20: 251.42 | C20: 312.3 | D20: 68.15 | E20: 129.88 | F20: 292.03 | H20: Loans (current) | I20: 0.64 | J20: 0.97 | K20: 0.95 | L20: 0.93 | M20: 0.93
A21: Profit before share of assoc./JV | B21: =B19-B20 -> 832.43 | C21: =C19-C20 -> 796.64 | D21: =D19-D20 -> 168.21 | E21: =E19-E20 -> 354.41 | F21: =F19-F20 -> 889.85 | H21: Other financial assets (current) | I21: 1.95 | J21: 16.31 | K21: 8.82 | L21: 5.86 | M21: 3.21
A22: Share of profit/(loss) - assoc/JV | B22: -0.2 | C22: -3.21 | D22: -5.94 | E22: 3.93 | F22: 0.29 | H22: Other current assets | I22: 151.6 | J22: 130.69 | K22: 175.22 | L22: 237.62 | M22: 214.17
A23: Profit for the year | B23: =B21+B22 -> 832.23 | C23: =C21+C22 -> 793.43 | D23: =D21+D22 -> 162.27 | E23: =E21+E22 -> 358.34 | F23: =F21+F22 -> 890.14 | H23: Total current assets | I23: =SUM(I16:I22) -> 3344.61 | J23: =SUM(J16:J22) -> 3461.68 | K23: =SUM(K16:K22) -> 3834.97 | L23: =SUM(L16:L22) -> 4332.32 | M23: =SUM(M16:M22) -> 4829.21
A24: Non-controlling interests (NCI) | B24: 4.71 | C24: 3.32 | D24: 1.72 | E24: 0.02 | F24: 1.35 | H24: TOTAL ASSETS | I24: =I15+I23 -> 6968.04 | J24: =J15+J23 -> 7660.4 | K24: =K15+K23 -> 8387.03 | L24: =L15+L23 -> 9335.57 | M24: =M15+M23 -> 10511.19
A25: PAT attributable to owners | B25: =B23-B24 -> 827.52 | C25: =C23-C24 -> 790.11 | D25: =D23-D24 -> 160.55 | E25: =E23-E24 -> 358.32 | F25: =F23-F24 -> 888.79 | H25: Equity share capital | I25: 107.47 | J25: 107.73 | K25: 107.79 | L25: 107.85 | M25: 107.97
H26: Other equity | I26: 3243.72 | J26: 3929.8 | K26: 4003.16 | L26: 4364.71 | M26: 5192.09
A27: CFO / Capex (Consolidated, per Cash Flow Statement) | H27: Equity attributable to owners | I27: =I25+I26 -> 3351.19 | J27: =J25+J26 -> 4037.53 | K27: =K25+K26 -> 4110.95 | L27: =L25+L26 -> 4472.56 | M27: =M25+M26 -> 5300.06
A28: Net cash from operating activities (CFO) | D28: 665.69 | E28: 601.65 | F28: 1623.5 | H28: Non-controlling interests | I28: 7.86 | J28: 11.13 | K28: 4.62 | L28: 129.96 | M28: 131.3
A29: Capital expenditure (purchase of PPE, incl. CWIP movement) | B29: -876.84 | C29: -990.16 | D29: -678.31 | E29: -641 | F29: -1069.95 | H29: Total equity | I29: =I27+I28 -> 3359.05 | J29: =J27+J28 -> 4048.66 | K29: =K27+K28 -> 4115.57 | L29: =L27+L28 -> 4602.52 | M29: =M27+M28 -> 5431.36
H30: Borrowings (non-current) | I30: 596.34 | J30: 761.42 | K30: 798.23 | L30: 645.58 | M30: 611.34
A31: KEY RATIOS (FY24A-FY26A, for reference/presentation) | H31: Lease liabilities (NC) | I31: 39.63 | J31: 37.44 | K31: 62.16 | L31: 62.19 | M31: 111.49
A32: Particulars | B32: FY22A | C32: FY23A | D32: FY24A | E32: FY25A | F32: FY26A | H32: Other financial liabilities (NC) | I32: 83.2 | J32: 91.2 | K32: 42.33 | L32: 0 | M32: 20.63
A33: ROCE % (EBIT / Capital Employed) | B33: =(B15-B16)/(I24-I44) -> 0.27630317 | C33: =(C15-C16)/(J24-J44) -> 0.24283015 | D33: =(D15-D16)/(K24-K44) -> 0.078420778 | E33: =(E15-E16)/(L24-L44) -> 0.11820872 | F33: =(F15-F16)/(M24-M44) -> 0.195766 | H33: Provisions (NC) | I33: 72.67 | J33: 81.47 | K33: 93.47 | L33: 106.09 | M33: 132.09
A34: ROE % (PAT attrib. owners / Equity attrib. owners) | B34: =B25/I27 -> 0.24693318 | C34: =C25/J27 -> 0.19569143 | D34: =D25/K27 -> 0.039054233 | E34: =E25/L27 -> 0.080115191 | F34: =F25/M27 -> 0.16769433 | H34: Deferred tax liability (net) | I34: 69.11 | J34: 82.45 | K34: 57.04 | L34: 31.87 | M34: 29.38
A35: Debt / Equity (Total debt / Total equity) | B35: =(I30+I37)/I29 -> 0.51563091 | C35: =(J30+J37)/J29 -> 0.48706733 | D35: =(K30+K37)/K29 -> 0.60916228 | E35: =(L30+L37)/L29 -> 0.58513162 | F35: =(M30+M37)/M29 -> 0.44141615 | H35: Other non-current liabilities | I35: 67.03 | J35: 125.5 | K35: 105.95 | L35: 347.6 | M35: 539.47
A36: EBIT margin % (EBIT / Revenue) | B36: =(B15-B16)/B6 -> 0.2399966 | C36: =(C15-C16)/C6 -> 0.21017126 | D36: =(D15-D16)/D6 -> 0.082059899 | E36: =(E15-E16)/E6 -> 0.12335703 | F36: =(F15-F16)/F6 -> 0.19757225 | H36: Total non-current liabilities | I36: =SUM(I30:I35) -> 927.98 | J36: =SUM(J30:J35) -> 1179.48 | K36: =SUM(K30:K35) -> 1159.18 | L36: =SUM(L30:L35) -> 1193.33 | M36: =SUM(M30:M35) -> 1444.4 | O36: Total debt
A37: PAT margin % (PAT attrib. owners / Revenue) | B37: =B25/B6 -> 0.16766453 | C37: =C25/C6 -> 0.130801 | D37: =D25/D6 -> 0.031849914 | E37: =E25/E6 -> 0.064516129 | F37: =F25/F6 -> 0.13045693 | H37: Borrowings (current) | I37: 1135.69 | J37: 1210.55 | K37: 1708.82 | L37: 2047.5 | M37: 1786.15 | O37: 611.34
H38: Trade payables | I38: 876.37 | J38: 710.65 | K38: 1051.24 | L38: 958.49 | M38: 1252.09 | O38: 1786.15
H39: Lease liabilities (current) | I39: 5 | J39: 5.68 | K39: 8.19 | L39: 8.46 | M39: 9.5 | O39: 111.49
H40: Other financial liabilities (current) | I40: 300.7 | J40: 192.33 | K40: 138.76 | L40: 337.61 | M40: 333.58 | O40: 9.5
H41: Other current liabilities | I41: 309.06 | J41: 227.96 | K41: 144.25 | L41: 101.12 | M41: 161.95
H42: Provisions (current) | I42: 16.49 | J42: 20.09 | K42: 24.81 | L42: 29.34 | M42: 37.89 | O42: =SUM(O37:O41) -> 2518.48
H43: Income tax liabilities (net) | I43: 37.7 | J43: 65 | K43: 36.21 | L43: 57.2 | M43: 54.27
H44: Total current liabilities | I44: =SUM(I37:I43) -> 2681.01 | J44: =SUM(J37:J43) -> 2432.26 | K44: =SUM(K37:K43) -> 3112.28 | L44: =SUM(L37:L43) -> 3539.72 | M44: =SUM(M37:M43) -> 3635.43
H45: TOTAL EQUITY + LIABILITIES | I45: =I29+I36+I44 -> 6968.04 | J45: =J29+J36+J44 -> 7660.4 | K45: =K29+K36+K44 -> 8387.03 | L45: =L29+L36+L44 -> 9335.57 | M45: =M29+M36+M44 -> 10511.19

Sheet Assumptions
B3: t-2 | C3: t-1 | D3: t0 | E3: t1 | F3: t2 | G3: t3 | H3: t4 | I3: t5
A4: Laurus Labs Ltd - Forecast Assumptions | B4: ACTUALS | E4: FORECAST
A5: Particulars | B5: FY24A | C5: FY25A | D5: FY26A | E5: FY27E | F5: FY28E | G5: FY29E | H5: FY30E | I5: FY31E | J5: Basis of this assumption | K5: Source
A6: REVENUE & MARGIN DRIVERS
A7: Revenue growth % YoY | B7: =Actuals!D6/Actuals!C6-1 -> -0.16550149 | C7: =Actuals!E6/Actuals!D6-1 -> 0.10179474 | D7: =Actuals!F6/Actuals!E6-1 -> 0.2266743 | E7: 0.15 | F7: 0.15 | G7: 0.15 | H7: 0.15 | I7: 0.15 | J7: 15% a year for FY27-31. FY26 grew +23% and 9M FY26 CDMO grew >50%; management expects 'healthy growth' in FY27 and 'significant growth in FY28' (Q3 FY26 call, Jan-2026) but gave no numbers. 15% is a moderated, round rate. | K7: AR FY25-26; Q3 FY26 concall (Jan-2026)
A8: Gross margin % | B8: =1-(Actuals!D9+Actuals!D10+Actuals!D11)/Actuals!D6 -> 0.51745645 | C8: =1-(Actuals!E9+Actuals!E10+Actuals!E11)/Actuals!E6 -> 0.55383546 | D8: =1-(Actuals!F9+Actuals!F10+Actuals!F11)/Actuals!F6 -> 0.60435938 | E8: 0.6 | F8: 0.6 | G8: 0.6 | H8: 0.6 | I8: 0.6 | J8: 60%: FY26 actual 60.4%; management expects 'to maintain gross margins of around 60%... also next financial year' (Q3 FY26 call, Jan-2026). | K8: AR FY25-26; Q3 FY26 concall
A9: Employee benefit expense % of revenue | B9: =Actuals!D12/Actuals!D6 -> 0.12694933 | C9: =Actuals!E12/Actuals!E6 -> 0.12955081 | D9: =Actuals!F12/Actuals!F6 -> 0.13143448 | E9: 0.13 | F9: 0.13 | G9: 0.13 | H9: 0.13 | I9: 0.13 | J9: 13%: FY26 actual 13.1%. | K9: AR FY25-26 (calculated)
A10: Other expenses % of revenue | B10: =Actuals!D13/Actuals!D6 -> 0.23626665 | C10: =Actuals!E13/Actuals!E6 -> 0.23427969 | D10: =Actuals!F13/Actuals!F6 -> 0.21199196 | E10: 0.21 | F10: 0.21 | G10: 0.21 | H10: 0.21 | I10: 0.21 | J10: 21%: FY26 actual 21.2%. Gives forecast EBITDA margin of 26% (60% - 13% - 21%) vs FY26 26.1% excluding other income. | K10: AR FY25-26 (calculated)
A11: Implied EBITDA margin % | B11: =Actuals!D15/Actuals!D6 -> 0.15835289 | C11: =Actuals!E15/Actuals!E6 -> 0.20079547 | D11: =Actuals!F15/Actuals!F6 -> 0.26803417 | E11: =E8-E9-E10 -> 0.26 | F11: =F8-F9-F10 -> 0.26 | G11: =G8-G9-G10 -> 0.26 | H11: =H8-H9-H10 -> 0.26 | I11: =I8-I9-I10 -> 0.26 | J11: Memo (formula): gross margin - employee % - other expenses %. Cross-check: FY26 EBITDA margin 26.8%, Q4 FY26 28.9% (Q4 FY26 call). Forecast EBITDA excludes other income.
A13: DEPRECIATION, TAX & FINANCE
A14: Depreciation & amortisation % of revenue | B14: =Actuals!D16/Actuals!D6 -> 0.076292991 | C14: =Actuals!E16/Actuals!E6 -> 0.07743844 | D14: =Actuals!F16/Actuals!F6 -> 0.070461918 | E14: 0.075 | F14: 0.075 | G14: 0.075 | H14: 0.075 | I14: 0.075 | J14: 7.5% (FY26 actual 7.05%): slightly higher as capex of over Rs1,000cr a year keeps adding to the asset base. | K14: AR FY25-26; Q3 FY26 concall
A15: Effective tax rate % | B15: =Actuals!D20/Actuals!D19 -> 0.28833136 | C15: =Actuals!E20/Actuals!E19 -> 0.26818642 | D15: =Actuals!F20/Actuals!F19 -> 0.24708938 | E15: 0.2517 | F15: 0.2517 | G15: 0.2517 | H15: 0.2517 | I15: 0.2517 | J15: 25.17% = India statutory corporate tax rate under the concessional regime (22% + 10% surcharge + 4% cess). FY26 effective rate 24.7% supports it. (Post-valuation-date corroboration only: CFO said ~25-26% in Apr-2026.) | K15: Statutory rate; AR FY25-26
A16: Effective interest rate (Finance costs / avg. total debt) | C16: =Actuals!E18/((Actuals!K30+Actuals!K37+Actuals!L30+Actuals!L37)/2) -> 0.083074846 | D16: =Actuals!F18/((Actuals!L30+Actuals!L37+Actuals!M30+Actuals!M37)/2) -> 0.067076968 | E16: 0.07 | F16: 0.07 | G16: 0.07 | H16: 0.07 | I16: 0.07 | J16: 7%: FY26 actual 6.7% (finance cost / average borrowings), rounded.
A17: Share of profit from associates/JV (Rs Cr, absolute) | B17: =Actuals!D22 -> -5.94 | C17: =Actuals!E22 -> 3.93 | D17: =Actuals!F22 -> 0.29 | E17: 0 | F17: 0 | G17: 0 | H17: 0 | I17: 0 | J17: Immaterial (Rs0.3cr in FY26); nil.
A18: NCI share % of Profit before NCI | B18: =Actuals!D24/Actuals!D23 -> 0.010599618 | C18: =Actuals!E24/Actuals!E23 -> 5.5812915e-05 | D18: =Actuals!F24/Actuals!F23 -> 0.0015166154 | E18: 0 | F18: 0 | G18: 0 | H18: 0 | I18: 0 | J18: Immaterial (0.15% of profit in FY26); nil.
A20: WORKING CAPITAL (days / % of revenue)
A21: Inventory / Revenue | B21: =Actuals!K16/Actuals!D6 -> 0.36609249 | C21: =Actuals!L16/Actuals!E6 -> 0.34867734 | D21: =Actuals!M16/Actuals!F6 -> 0.34378312 | E21: 0.34 | F21: 0.34 | G21: 0.34 | H21: 0.34 | I21: 0.34 | J21: 34%: FY26 actual 34.4%; held flat.
A22: Trade receivables / Revenue | B22: =Actuals!K17/Actuals!D6 -> 0.32989012 | C22: =Actuals!L17/Actuals!E6 -> 0.36139259 | D22: =Actuals!M17/Actuals!F6 -> 0.31631757 | E22: 0.32 | F22: 0.32 | G22: 0.32 | H22: 0.32 | I22: 0.32 | J22: 32%: FY26 actual 31.6%; held flat.
A23: Trade payables / Revenue | B23: =Actuals!K38/Actuals!D6 -> 0.20854502 | C23: =Actuals!L38/Actuals!E6 -> 0.17257776 | D23: =Actuals!M38/Actuals!F6 -> 0.18378224 | E23: 0.18 | F23: 0.18 | G23: 0.18 | H23: 0.18 | I23: 0.18 | J23: 18%: FY26 actual 18.4%; held flat.
A24: Other operating current assets / Revenue | B24: =Actuals!K22/Actuals!D6 -> 0.034760149 | C24: =Actuals!L22/Actuals!E6 -> 0.042783888 | D24: =Actuals!M22/Actuals!F6 -> 0.031435952 | E24: 0.03 | F24: 0.03 | G24: 0.03 | H24: 0.03 | I24: 0.03 | J24: 3%: FY26 actual 3.1%; held flat.
A25: Other operating current liabilities / Revenue | B25: =Actuals!K41/Actuals!D6 -> 0.028616319 | C25: =Actuals!L41/Actuals!E6 -> 0.018206829 | D25: =Actuals!M41/Actuals!F6 -> 0.023771081 | E25: 0.02 | F25: 0.02 | G25: 0.02 | H25: 0.02 | I25: 0.02 | J25: 2%: FY26 actual 2.4%; rounded.
A27: CAPEX & SHARE COUNT
A28: Capital expenditure (Rs Crore, absolute) | B28: =-Actuals!D29 -> 678.31 | C28: =-Actuals!E29 -> 641 | D28: =-Actuals!F29 -> 1069.95 | E28: 1200 | F28: 1200 | G28: 1200 | H28: 1200 | I28: 1200 | J28: Rs1,200cr a year: management said capex is about Rs1,000cr in FY26 and 'over Rs1,000 crores next year also' (Q3 FY26 call, Jan-2026); FY26 actual Rs1,070cr. Rs1,200cr held flat. (Post-valuation-date corroboration only, not used: Apr-2026 call raised guidance to ~Rs1,500cr a year.) | K28: Q3 FY26 concall (Jan-2026); AR FY25-26
A29: Shares outstanding, period-end 31-Mar-2026 (Crore) - for market cap & value per share | D29: 53.985658 | E29: 53.985658 | F29: 53.985658 | G29: 53.985658 | H29: 53.985658 | I29: 53.985658 | J29: Period-end shares at 31-Mar-2026: 53.9856582 Cr (539,856,582 shares). USED FOR market capitalisation and value per share.
A30: Diluted weighted-average shares FY26 (Crore) - for EPS only | D30: 54.045959 | J30: FY26 diluted weighted-average shares, used ONLY for FY26 EPS / P/E. Not used for market cap or value per share. | K30: AR FY25-26 (EPS note)
B32: t-2 | C32: t-1 | D32: t0 | E32: t1 | F32: t2 | G32: t3 | H32: t4 | I32: t5
A33: Balance Sheet Assumptions | B33: ACTUALS | E33: FORECAST
A34: Particulars | B34: FY24A | C34: FY25A | D34: FY26A | E34: FY27E | F34: FY28E | G34: FY29E | H34: FY30E | I34: FY31E
A35: PPE / Revenue (memo; PPE forecast uses roll-forward) | B35: =Actuals!K6/Actuals!$D$6 -> 0.68369098 | C35: =Actuals!L6/Actuals!E6 -> 0.6605125 | D35: =Actuals!M6/Actuals!F6 -> 0.56851414 | E35: 0.5685 | F35: 0.5685 | G35: 0.5685 | H35: 0.5685 | I35: 0.5685 | J35: PPE/revenue held near FY26A
A36: Right-of-use assets / Revenue | B36: =Actuals!K7/Actuals!$D$6 -> 0.035375127 | C36: =Actuals!L7/Actuals!$E$6 -> 0.034054981 | D36: =Actuals!M7/Actuals!$F$6 -> 0.03415726 | E36: 0.0342 | F36: 0.0342 | G36: 0.0342 | H36: 0.0342 | I36: 0.0342 | J36: ROU assets/revenue held near FY26A
A37: Capital work-in-progress / Revenue | B37: =Actuals!K8/Actuals!$D$6 -> 0.083883011 | C37: =Actuals!L8/Actuals!$E$6 -> 0.082528502 | D37: =Actuals!M8/Actuals!$F$6 -> 0.11350233 | E37: 0.1135 | F37: 0.1135 | G37: 0.1135 | H37: 0.1135 | I37: 0.1135 | J37: CWIP/revenue held near FY26A
A38: Goodwill / Revenue | B38: =Actuals!K9/Actuals!$D$6 -> 0.048861001 | C38: =Actuals!L9/Actuals!$E$6 -> 0.044346736 | D38: =Actuals!M9/Actuals!$F$6 -> 0.036152006 | E38: 0.0362 | F38: 0.0362 | G38: 0.0362 | H38: 0.0362 | I38: 0.0362 | J38: Goodwill/revenue held near FY26A
A39: Other intangible assets / Revenue | B39: =Actuals!K10/Actuals!$D$6 -> 0.0037731881 | C39: =Actuals!L10/Actuals!$E$6 -> 0.0034785991 | D39: =Actuals!M10/Actuals!$F$6 -> 0.0027007589 | E39: 0.0027 | F39: 0.0027 | G39: 0.0027 | H39: 0.0027 | I39: 0.0027 | J39: Intangibles/revenue held near FY26A
A40: Investments (non-current) / Revenue | B40: =Actuals!K11/Actuals!$D$6 -> 0.024595156 | C40: =Actuals!L11/Actuals!$E$6 -> 0.041998862 | D40: =Actuals!M11/Actuals!$F$6 -> 0.045394766 | E40: 0.0454 | F40: 0.0454 | G40: 0.0454 | H40: 0.0454 | I40: 0.0454 | J40: Non-operating investments/revenue held near FY26A
A41: Other financial assets (NC) / Revenue | B41: =Actuals!K12/Actuals!$D$6 -> 0.0093992458 | C41: =Actuals!L12/Actuals!$E$6 -> 0.0087613163 | D41: =Actuals!M12/Actuals!$F$6 -> 0.0064964993 | E41: 0.0065 | F41: 0.0065 | G41: 0.0065 | H41: 0.0065 | I41: 0.0065 | J41: Held near FY26A as % of revenue
A42: Income tax assets (NC) / Revenue | B42: =Actuals!K13/Actuals!$D$6 -> 0.00058918869 | C42: =Actuals!L13/Actuals!$E$6 -> 0.0012495589 | D42: =Actuals!M13/Actuals!$F$6 -> 0.00035814411 | E42: 0.0004 | F42: 0.0004 | G42: 0.0004 | H42: 0.0004 | I42: 0.0004 | J42: Held near FY26A; immaterial
A43: Other non-current assets / Revenue | B43: =Actuals!K14/Actuals!$D$6 -> 0.012870896 | C43: =Actuals!L14/Actuals!$E$6 -> 0.023912668 | D43: =Actuals!M14/Actuals!$F$6 -> 0.026727238 | E43: 0.0267 | F43: 0.0267 | G43: 0.0267 | H43: 0.0267 | I43: 0.0267 | J43: Held near FY26A as % of revenue
A44: Other bank balances / Revenue | B44: =Actuals!I19/Actuals!$D$6 -> 0.00011704422 | C44: =Actuals!J19/Actuals!$D$6 -> 0.00055348028 | D44: =Actuals!K19/Actuals!$D$6 -> 0.00053760988 | E44: 0.0002 | F44: 0.0002 | G44: 0.0002 | H44: 0.0002 | I44: 0.0002 | J44: Held near FY26A; immaterial
A45: Loans (current) / Revenue | B45: =Actuals!I20/Actuals!$D$6 -> 0.00012696322 | C45: =Actuals!J20/Actuals!$D$6 -> 0.00019242863 | D45: =Actuals!K20/Actuals!$D$6 -> 0.00018846103 | E45: 0.0001 | F45: 0.0001 | G45: 0.0001 | H45: 0.0001 | I45: 0.0001 | J45: Held near FY26A; immaterial
A46: Other financial assets (current) / Revenue | B46: =Actuals!I21/Actuals!$D$6 -> 0.00038684106 | C46: =Actuals!J21/Actuals!$D$6 -> 0.0032355783 | D46: =Actuals!K21/Actuals!$D$6 -> 0.0017497119 | E46: 0.0005 | F46: 0.0005 | G46: 0.0005 | H46: 0.0005 | I46: 0.0005 | J46: Held near FY26A; immaterial
A47: Equity share capital (Rs Cr, absolute) | B47: =Actuals!K25 -> 107.79 | C47: =Actuals!L25 -> 107.85 | D47: =Actuals!M25 -> 107.97 | E47: =$D$47 -> 107.97 | F47: =$D$47 -> 107.97 | G47: =$D$47 -> 107.97 | H47: =$D$47 -> 107.97 | I47: =$D$47 -> 107.97 | J47: Held flat at FY26A
A48: NCI / Revenue | B48: =Actuals!K28/Actuals!D6 -> 0.00091651573 | C48: =Actuals!L28/Actuals!E6 -> 0.02339952 | D48: =Actuals!M28/Actuals!$F$6 -> 0.019272263 | E48: =Actuals!$M$28 -> 131.3 | F48: =Actuals!$M$28 -> 131.3 | G48: =Actuals!$M$28 -> 131.3 | H48: =Actuals!$M$28 -> 131.3 | I48: =Actuals!$M$28 -> 131.3 | J48: Hold NCI at FY26A ₹131.30 Cr, unless there is a specific NCI roll-forward assumption.
A49: Borrowings (non-current) - held flat at FY26A (Rs Cr) | B49: =Actuals!K30 -> 798.23 | C49: =Actuals!L30 -> 645.58 | D49: =Actuals!M30 -> 611.34 | E49: =Actuals!$M$30 -> 611.34 | F49: =Actuals!$M$30 -> 611.34 | G49: =Actuals!$M$30 -> 611.34 | H49: =Actuals!$M$30 -> 611.34 | I49: =Actuals!$M$30 -> 611.34 | J49: Held flat at FY26A absolute borrowing
A50: Lease liabilities (NC) / Revenue | B50: =Actuals!K31/Actuals!$D$6 -> 0.012331303 | C50: =Actuals!L31/Actuals!$E$6 -> 0.011197416 | D50: =Actuals!M31/Actuals!$F$6 -> 0.016364544 | E50: 0.0164 | F50: 0.0164 | G50: 0.0164 | H50: 0.0164 | I50: 0.0164 | J50: Held near FY26A as % of revenue
A51: Other financial liabilities (NC) / Revenue | B51: =Actuals!K32/Actuals!$D$6 -> 0.0083974266 | C51: =Actuals!L32/Actuals!$E$6 -> 0 | D51: =Actuals!M32/Actuals!$F$6 -> 0.0030280791 | E51: 0.003 | F51: 0.003 | G51: 0.003 | H51: 0.003 | I51: 0.003 | J51: Held near FY26A as % of revenue
A52: Provisions (NC) / Revenue | B52: =Actuals!K33/Actuals!$D$6 -> 0.018542581 | C52: =Actuals!L33/Actuals!$E$6 -> 0.019101686 | D52: =Actuals!M33/Actuals!$F$6 -> 0.019388219 | E52: 0.0194 | F52: 0.0194 | G52: 0.0194 | H52: 0.0194 | I52: 0.0194 | J52: Held near FY26A as % of revenue
A53: Deferred tax liability / Revenue | B53: =Actuals!K34/Actuals!$D$6 -> 0.011315597 | C53: =Actuals!L34/Actuals!$E$6 -> 0.005738248 | D53: =Actuals!M34/Actuals!$F$6 -> 0.0043124073 | E53: 0.0043 | F53: 0.0043 | G53: 0.0043 | H53: 0.0043 | I53: 0.0043 | J53: Held near FY26A as % of revenue
A54: Other non-current liabilities / Revenue | B54: =Actuals!K35/Actuals!$D$6 -> 0.021018364 | C54: =Actuals!L35/Actuals!$E$6 -> 0.062585975 | D54: =Actuals!M35/Actuals!$F$6 -> 0.079183608 | E54: 0.0792 | F54: 0.0792 | G54: 0.0792 | H54: 0.0792 | I54: 0.0792 | J54: Held near FY26A as % of revenue
A55: Borrowings (current) - held flat at FY26A (Rs Cr) | B55: =Actuals!K37 -> 1708.82 | C55: =Actuals!L37 -> 2047.5 | D55: =Actuals!M37 -> 1786.15 | E55: =Actuals!$M$37 -> 1786.15 | F55: =Actuals!$M$37 -> 1786.15 | G55: =Actuals!$M$37 -> 1786.15 | H55: =Actuals!$M$37 -> 1786.15 | I55: =Actuals!$M$37 -> 1786.15 | J55: Base current borrowings held at FY26A; deficit funding added via STB plug when required
A56: Lease liabilities (current) / Revenue | B56: =Actuals!K39/Actuals!$D$6 -> 0.0016247324 | C56: =Actuals!L39/Actuals!$E$6 -> 0.0015232375 | D56: =Actuals!M39/Actuals!$F$6 -> 0.0013944135 | E56: 0.0014 | F56: 0.0014 | G56: 0.0014 | H56: 0.0014 | I56: 0.0014 | J56: Held near FY26A as % of revenue
A57: Other financial liabilities (current) / Revenue | B57: =Actuals!K40/Actuals!$D$6 -> 0.027527213 | C57: =Actuals!L40/Actuals!$E$6 -> 0.060787258 | D57: =Actuals!M40/Actuals!$F$6 -> 0.048962997 | E57: 0.049 | F57: 0.049 | G57: 0.049 | H57: 0.049 | I57: 0.049 | J57: Held near FY26A as % of revenue
A58: Provisions (current) / Revenue | B58: =Actuals!K41/Actuals!$D$6 -> 0.028616319 | C58: =Actuals!L41/Actuals!$E$6 -> 0.018206829 | D58: =Actuals!M41/Actuals!$F$6 -> 0.023771081 | E58: 0.0056 | F58: 0.0056 | G58: 0.0056 | H58: 0.0056 | I58: 0.0056 | J58: Held near FY26A as % of revenue
A59: Income tax liabilities / Revenue | B59: =Actuals!K42/Actuals!$D$6 -> 0.0049218085 | C59: =Actuals!L42/Actuals!$E$6 -> 0.0052827172 | D59: =Actuals!M42/Actuals!$F$6 -> 0.0055615083 | E59: 0.008 | F59: 0.008 | G59: 0.008 | H59: 0.008 | I59: 0.008 | J59: Held near FY26A as % of revenue
A61: Cash & cash equivalents | E61: Balancing figure | J61: Cash is kept non-negative; any forecast funding deficit is assumed to be met through short-term borrowings.
A62: Dividend payout ratio (for retained earnings roll-forward) | E62: 0.2 | F62: 0.2 | G62: 0.2 | H62: 0.2 | I62: 0.2 | J62: 20% payout ratio used for retained earnings roll-forward

Sheet Cost of Capital
A1: Laurus Labs Ltd - Cost of Capital (WACC)
A4: COST OF EQUITY (CAPM) | C4: Source
A5: Risk-free rate (India 10-yr G-Sec yield) | B5: 0.0696 | C5: RBI: India 10-Year Bond Yield Historical Data
A6: Levered Beta (Beta) | B6: 1.0656 | C6: Capitaline AWS. Beta against Nifty 50 on 31st March 2026
A7: Equity risk premium (India) | B7: 0.07 | C7: India Equity Risk Premium from Aswath Damodaran
A8: Cost of equity (Ke) = Rf + Beta x ERP | B8: =B5+B6*B7 -> 0.144192
A10: COST OF DEBT
A11: Pre-tax cost of debt (effective interest rate) | B11: =Assumptions!D16 -> 0.067076968 | C11: FY26 finance costs / average total borrowings
A12: Tax rate (for after-tax Kd) | B12: =Assumptions!E15 -> 0.2517 | C12: Same rate used in NOPAT
A13: After-tax cost of debt = Kd x (1-Tax) | B13: =B11*(1-B12) -> 0.050193695
A15: CAPITAL STRUCTURE (market-value based)
A16: Debt incl. lease liabilities (Rs Cr, FY26A, book value) | B16: =Actuals!M30+Actuals!M31+Actuals!M37+Actuals!M39 -> 2518.48 | C16: Borrowings (non-current + current) + lease liabilities at 31-Mar-2026
A17: Current share price (Rs) | B17: 992.7 | C17: NSE closing price on 30-Mar-2026
A18: Shares outstanding, period-end 31-Mar-2026 (Crore) | B18: =Assumptions!D29 -> 53.985658 | C18: Period-end share count, used for market capitalisation (not the EPS share count).
A19: Market value of equity (Rs Cr) | B19: =B17*B18 -> 53591.563 | C19: Current share price x Shares outstanding
A20: D / (D+E) | B20: =B16/(B16+B19) -> 0.044884656
A21: E / (D+E) | B21: =B19/(B16+B19) -> 0.95511534
A23: WACC | B23: =(B8*B21)+(B13*B20) -> 0.13997292
A25: TERMINAL GROWTH RATE | B25: 0.04 | C25: Sustainable long-term nominal growth assumption not the company’s temporary high-growth phase.

Sheet Forecast 1 (Growth-Margin)
A2: Laurus Labs Ltd - Forecast 1: Revenue Growth / Operating Margin Approach | B2: t0 | C2: t1 | D2: t2 | E2: t3 | F2: t4 | G2: t5
B3: ACTUAL | C3: FORECAST
A4: Particulars | B4: FY26A | C4: FY27E | D4: FY28E | E4: FY29E | F4: FY30E | G4: FY31E
A5: PROFIT & LOSS
A6: Revenue from operations | B6: =Actuals!F6 -> 6812.9 | C6: =B6*(1+Assumptions!E7) -> 7834.835 | D6: =C6*(1+Assumptions!F7) -> 9010.0602 | E6: =D6*(1+Assumptions!G7) -> 10361.569 | F6: =E6*(1+Assumptions!H7) -> 11915.805 | G6: =F6*(1+Assumptions!I7) -> 13703.175
A7: Gross profit (Revenue x Gross margin%) | B7: =B6*Assumptions!D8 -> 4117.44 | C7: =C6*Assumptions!E8 -> 4700.901 | D7: =D6*Assumptions!F8 -> 5406.0361 | E7: =E6*Assumptions!G8 -> 6216.9416 | F7: =F6*Assumptions!H8 -> 7149.4828 | G7: =G6*Assumptions!I8 -> 8221.9052
A8: Employee benefits expense | B8: =B6*Assumptions!D9 -> 895.45 | C8: =C6*Assumptions!E9 -> 1018.5285 | D8: =D6*Assumptions!F9 -> 1171.3078 | E8: =E6*Assumptions!G9 -> 1347.004 | F8: =F6*Assumptions!H9 -> 1549.0546 | G8: =G6*Assumptions!I9 -> 1781.4128
A9: Other expenses | B9: =B6*Assumptions!D10 -> 1444.28 | C9: =C6*Assumptions!E10 -> 1645.3153 | D9: =D6*Assumptions!F10 -> 1892.1127 | E9: =E6*Assumptions!G10 -> 2175.9296 | F9: =F6*Assumptions!H10 -> 2502.319 | G9: =G6*Assumptions!I10 -> 2877.6668
A10: EBITDA | B10: =Actuals!F15 -> 1826.09 | C10: =C7-C8-C9 -> 2037.0571 | D10: =D7-D8-D9 -> 2342.6157 | E10: =E7-E8-E9 -> 2694.008 | F10: =F7-F8-F9 -> 3098.1092 | G10: =G7-G8-G9 -> 3562.8256
A11: Depreciation & amortisation | B11: =Actuals!F16 -> 480.05 | C11: =C6*Assumptions!E14 -> 587.61262 | D11: =D6*Assumptions!F14 -> 675.75452 | E11: =E6*Assumptions!G14 -> 777.1177 | F11: =F6*Assumptions!H14 -> 893.68535 | G11: =G6*Assumptions!I14 -> 1027.7382
A12: EBIT | B12: =B10-B11 -> 1346.04 | C12: =C10-C11 -> 1449.4445 | D12: =D10-D11 -> 1666.8611 | E12: =E10-E11 -> 1916.8903 | F12: =F10-F11 -> 2204.4239 | G12: =G10-G11 -> 2535.0874
A13: Total debt balance | B13: =Actuals!M30+Actuals!M37 -> 2397.49 | C13: =$B$13 -> 2397.49 | D13: =$B$13 -> 2397.49 | E13: =$B$13 -> 2397.49 | F13: =$B$13 -> 2397.49 | G13: =$B$13 -> 2397.49
A14: Interest expense | B14: =Actuals!F18 -> 170.73 | C14: =C13*Assumptions!E16 -> 167.8243 | D14: =D13*Assumptions!F16 -> 167.8243 | E14: =E13*Assumptions!G16 -> 167.8243 | F14: =F13*Assumptions!H16 -> 167.8243 | G14: =G13*Assumptions!I16 -> 167.8243
A15: Finance income | B15: =-Actuals!F17 -> 6.57 | C15: =-Actuals!$F$17 -> 6.57 | D15: =-Actuals!$F$17 -> 6.57 | E15: =-Actuals!$F$17 -> 6.57 | F15: =-Actuals!$F$17 -> 6.57 | G15: =-Actuals!$F$17 -> 6.57
A16: Profit before tax (EBT) | B16: =Actuals!F19 -> 1181.88 | C16: =C12-C14+C15 -> 1288.1902 | D16: =D12-D14+D15 -> 1505.6068 | E16: =E12-E14+E15 -> 1755.636 | F16: =F12-F14+F15 -> 2043.1696 | G16: =G12-G14+G15 -> 2373.8331
A17: Tax expense | B17: =Actuals!F20 -> 292.03 | C17: =C16*Assumptions!E15 -> 324.23747 | D17: =D16*Assumptions!F15 -> 378.96124 | E17: =E16*Assumptions!G15 -> 441.89359 | F17: =F16*Assumptions!H15 -> 514.26578 | G17: =G16*Assumptions!I15 -> 597.4938
A18: Share of profit from associates/JV | B18: =Actuals!F22 -> 0.29 | C18: =Assumptions!E17 -> 0 | D18: =Assumptions!F17 -> 0 | E18: =Assumptions!G17 -> 0 | F18: =Assumptions!H17 -> 0 | G18: =Assumptions!I17 -> 0
A19: Profit before NCI | B19: =Actuals!F23 -> 890.14 | C19: =C16-C17+C18 -> 963.95271 | D19: =D16-D17+D18 -> 1126.6456 | E19: =E16-E17+E18 -> 1313.7424 | F19: =F16-F17+F18 -> 1528.9038 | G19: =G16-G17+G18 -> 1776.3393
A20: Non-controlling interests | B20: =Actuals!F24 -> 1.35 | C20: =C19*Assumptions!E18 -> 0 | D20: =D19*Assumptions!F18 -> 0 | E20: =E19*Assumptions!G18 -> 0 | F20: =F19*Assumptions!H18 -> 0 | G20: =G19*Assumptions!I18 -> 0
A21: PAT attributable to owners | B21: =Actuals!F25 -> 888.79 | C21: =C19-C20 -> 963.95271 | D21: =D19-D20 -> 1126.6456 | E21: =E19-E20 -> 1313.7424 | F21: =F19-F20 -> 1528.9038 | G21: =G19-G20 -> 1776.3393
A22: EPS (Rs, diluted) - memo | B22: =B21/Assumptions!D29 -> 16.463447 | C22: =C21/Assumptions!E29 -> 17.855718 | D22: =D21/Assumptions!F29 -> 20.86935 | E22: =E21/Assumptions!G29 -> 24.335027 | F22: =F21/Assumptions!H29 -> 28.320555 | G22: =G21/Assumptions!I29 -> 32.903912
A24: WORKING CAPITAL & CAPEX (for FCFF build)
A25: Inventory | B25: =Actuals!M16 -> 2342.16 | C25: =C6*Assumptions!E21 -> 2663.8439 | D25: =D6*Assumptions!F21 -> 3063.4205 | E25: =E6*Assumptions!G21 -> 3522.9336 | F25: =F6*Assumptions!H21 -> 4051.3736 | G25: =G6*Assumptions!I21 -> 4659.0796
A26: Trade receivables | B26: =Actuals!M17 -> 2155.04 | C26: =C6*Assumptions!E22 -> 2507.1472 | D26: =D6*Assumptions!F22 -> 2883.2193 | E26: =E6*Assumptions!G22 -> 3315.7022 | F26: =F6*Assumptions!H22 -> 3813.0575 | G26: =G6*Assumptions!I22 -> 4385.0161
A27: Other operating current assets | B27: =Actuals!M22 -> 214.17 | C27: =C6*Assumptions!E24 -> 235.04505 | D27: =D6*Assumptions!F24 -> 270.30181 | E27: =E6*Assumptions!G24 -> 310.84708 | F27: =F6*Assumptions!H24 -> 357.47414 | G27: =G6*Assumptions!I24 -> 411.09526
A28: Trade payables | B28: =Actuals!M38 -> 1252.09 | C28: =C6*Assumptions!E23 -> 1410.2703 | D28: =D6*Assumptions!F23 -> 1621.8108 | E28: =E6*Assumptions!G23 -> 1865.0825 | F28: =F6*Assumptions!H23 -> 2144.8448 | G28: =G6*Assumptions!I23 -> 2466.5716
A29: Other operating current liabilities | B29: =Actuals!M41 -> 161.95 | C29: =C6*Assumptions!E25 -> 156.6967 | D29: =D6*Assumptions!F25 -> 180.2012 | E29: =E6*Assumptions!G25 -> 207.23139 | F29: =F6*Assumptions!H25 -> 238.31609 | G29: =G6*Assumptions!I25 -> 274.06351
A30: Operating Working Capital (OWC) | B30: =B25+B26+B27-B28-B29 -> 3297.33 | C30: =C25+C26+C27-C28-C29 -> 3839.0691 | D30: =D25+D26+D27-D28-D29 -> 4414.9295 | E30: =E25+E26+E27-E28-E29 -> 5077.169 | F30: =F25+F26+F27-F28-F29 -> 5838.7443 | G30: =G25+G26+G27-G28-G29 -> 6714.5559
A31: Change in OWC (increase = cash outflow) | C31: =C30-B30 -> 541.73915 | D31: =D30-C30 -> 575.86037 | E31: =E30-D30 -> 662.23943 | F31: =F30-E30 -> 761.57534 | G31: =G30-F30 -> 875.81164
A32: Capital expenditure | B32: =-Actuals!F29 -> 1069.95 | C32: =Assumptions!E28 -> 1200 | D32: =Assumptions!F28 -> 1200 | E32: =Assumptions!G28 -> 1200 | F32: =Assumptions!H28 -> 1200 | G32: =Assumptions!I28 -> 1200
A34: Balance Sheet | B34: t0 | C34: t1 | D34: t2 | E34: t3 | F34: t4 | G34: t5
B35: ACTUAL | C35: FORECAST
A36: Particulars | B36: FY26A | C36: FY27E | D36: FY28E | E36: FY29E | F36: FY30E | G36: FY31E
A37: Property, plant & equipment | B37: =Actuals!M6 -> 3873.23 | C37: =B37+C32-C11 -> 4485.6174 | D37: =C37+D32-D11 -> 5009.8629 | E37: =D37+E32-E11 -> 5432.7452 | F37: =E37+F32-F11 -> 5739.0598 | G37: =F37+G32-G11 -> 5911.3217
A38: Right-of-use assets | B38: =Actuals!M7 -> 232.71 | C38: =C6*Assumptions!E36 -> 267.95136 | D38: =D6*Assumptions!F36 -> 308.14406 | E38: =E6*Assumptions!G36 -> 354.36567 | F38: =F6*Assumptions!H36 -> 407.52052 | G38: =G6*Assumptions!I36 -> 468.6486
A39: Capital work-in-progress | B39: =Actuals!M8 -> 773.28 | C39: =C6*Assumptions!E37 -> 889.25377 | D39: =D6*Assumptions!F37 -> 1022.6418 | E39: =E6*Assumptions!G37 -> 1176.0381 | F39: =F6*Assumptions!H37 -> 1352.4438 | G39: =G6*Assumptions!I37 -> 1555.3104
A40: Goodwill | B40: =Actuals!M9 -> 246.3 | C40: =C6*Assumptions!E38 -> 283.62103 | D40: =D6*Assumptions!F38 -> 326.16418 | E40: =E6*Assumptions!G38 -> 375.08881 | F40: =F6*Assumptions!H38 -> 431.35213 | G40: =G6*Assumptions!I38 -> 496.05495
A41: Other intangible assets | B41: =Actuals!M10 -> 18.4 | C41: =C6*Assumptions!E39 -> 21.154054 | D41: =D6*Assumptions!F39 -> 24.327163 | E41: =E6*Assumptions!G39 -> 27.976237 | F41: =F6*Assumptions!H39 -> 32.172673 | G41: =G6*Assumptions!I39 -> 36.998574
A42: Investments (non-current) | B42: =Actuals!M11 -> 309.27 | C42: =C6*Assumptions!E40 -> 355.70151 | D42: =D6*Assumptions!F40 -> 409.05674 | E42: =E6*Assumptions!G40 -> 470.41525 | F42: =F6*Assumptions!H40 -> 540.97753 | G42: =G6*Assumptions!I40 -> 622.12416
A43: Other financial assets (NC) | B43: =Actuals!M12 -> 44.26 | C43: =C6*Assumptions!E41 -> 50.926427 | D43: =D6*Assumptions!F41 -> 58.565392 | E43: =E6*Assumptions!G41 -> 67.3502 | F43: =F6*Assumptions!H41 -> 77.45273 | G43: =G6*Assumptions!I41 -> 89.07064
A44: Income tax assets (NC) | B44: =Actuals!M13 -> 2.44 | C44: =C6*Assumptions!E42 -> 3.133934 | D44: =D6*Assumptions!F42 -> 3.6040241 | E44: =E6*Assumptions!G42 -> 4.1446277 | F44: =F6*Assumptions!H42 -> 4.7663219 | G44: =G6*Assumptions!I42 -> 5.4812702
A45: Other non-current assets | B45: =Actuals!M14 -> 182.09 | C45: =C6*Assumptions!E43 -> 209.19009 | D45: =D6*Assumptions!F43 -> 240.56861 | E45: =E6*Assumptions!G43 -> 276.6539 | F45: =F6*Assumptions!H43 -> 318.15198 | G45: =G6*Assumptions!I43 -> 365.87478
A46: Total non-current assets | B46: =SUM(B37:B45) -> 5681.98 | C46: =SUM(C37:C45) -> 6566.5496 | D46: =SUM(D37:D45) -> 7402.9349 | E46: =SUM(E37:E45) -> 8184.778 | F46: =SUM(F37:F45) -> 8903.8975 | G46: =SUM(G37:G45) -> 9550.885
A47: ASSETS - CURRENT
A48: Inventory | B48: =Actuals!M16 -> 2342.16 | C48: =C6*Assumptions!E21 -> 2663.8439 | D48: =D6*Assumptions!F21 -> 3063.4205 | E48: =E6*Assumptions!G21 -> 3522.9336 | F48: =F6*Assumptions!H21 -> 4051.3736 | G48: =G6*Assumptions!I21 -> 4659.0796
A49: Trade receivables | B49: =Actuals!M17 -> 2155.04 | C49: =C6*Assumptions!E22 -> 2507.1472 | D49: =D6*Assumptions!F22 -> 2883.2193 | E49: =E6*Assumptions!G22 -> 3315.7022 | F49: =F6*Assumptions!H22 -> 3813.0575 | G49: =G6*Assumptions!I22 -> 4385.0161
A50: Cash & cash equivalents | B50: =Actuals!M18 -> 112.66 | C50: =MAX(0,(C61+C69+C71+C72+C73+C74+C75+C76+C77)-(C46+C48+C49+C51+C52+C53+C54)) -> 0 | D50: =MAX(0,(D61+D69+D71+D72+D73+D74+D75+D76+D77)-(D46+D48+D49+D51+D52+D53+D54)) -> 0 | E50: =MAX(0,(E61+E69+E71+E72+E73+E74+E75+E76+E77)-(E46+E48+E49+E51+E52+E53+E54)) -> 0 | F50: =MAX(0,(F61+F69+F71+F72+F73+F74+F75+F76+F77)-(F46+F48+F49+F51+F52+F53+F54)) -> 0 | G50: =MAX(0,(G61+G69+G71+G72+G73+G74+G75+G76+G77)-(G46+G48+G49+G51+G52+G53+G54)) -> 0
A51: Other bank balances | B51: =Actuals!M19 -> 1.04 | C51: =C6*Assumptions!E44 -> 1.566967 | D51: =D6*Assumptions!F44 -> 1.802012 | E51: =E6*Assumptions!G44 -> 2.0723139 | F51: =F6*Assumptions!H44 -> 2.3831609 | G51: =G6*Assumptions!I44 -> 2.7406351
A52: Loans (current) | B52: =Actuals!M20 -> 0.93 | C52: =C6*Assumptions!E45 -> 0.7834835 | D52: =D6*Assumptions!F45 -> 0.90100602 | E52: =E6*Assumptions!G45 -> 1.0361569 | F52: =F6*Assumptions!H45 -> 1.1915805 | G52: =G6*Assumptions!I45 -> 1.3703175
A53: Other financial assets (current) | B53: =Actuals!M21 -> 3.21 | C53: =C6*Assumptions!E46 -> 3.9174175 | D53: =D6*Assumptions!F46 -> 4.5050301 | E53: =E6*Assumptions!G46 -> 5.1807846 | F53: =F6*Assumptions!H46 -> 5.9579023 | G53: =G6*Assumptions!I46 -> 6.8515877
A54: Other current assets | B54: =Actuals!M22 -> 214.17 | C54: =C6*Assumptions!E24 -> 235.04505 | D54: =D6*Assumptions!F24 -> 270.30181 | E54: =E6*Assumptions!G24 -> 310.84708 | F54: =F6*Assumptions!H24 -> 357.47414 | G54: =G6*Assumptions!I24 -> 411.09526
A55: Total current assets | B55: =SUM(B48:B54) -> 4829.21 | C55: =SUM(C48:C54) -> 5412.304 | D55: =SUM(D48:D54) -> 6224.1496 | E55: =SUM(E48:E54) -> 7157.7721 | F55: =SUM(F48:F54) -> 8231.4379 | G55: =SUM(G48:G54) -> 9466.1536
A56: TOTAL ASSETS | B56: =B46+B55 -> 10511.19 | C56: =C46+C55 -> 11978.854 | D56: =D46+D55 -> 13627.084 | E56: =E46+E55 -> 15342.55 | F56: =F46+F55 -> 17135.335 | G56: =G46+G55 -> 19017.039
A57: EQUITY & LIABILITIES
A58: Equity share capital | B58: =Actuals!M25 -> 107.97 | C58: =Assumptions!$D$47 -> 107.97 | D58: =Assumptions!$D$47 -> 107.97 | E58: =Assumptions!$D$47 -> 107.97 | F58: =Assumptions!$D$47 -> 107.97 | G58: =Assumptions!$D$47 -> 107.97
A59: Other equity (retained earnings roll-forward) | B59: =Actuals!M26 -> 5192.09 | C59: =B59+C21-C21*Assumptions!E62 -> 5963.2522 | D59: =C59+D21-D21*Assumptions!F62 -> 6864.5686 | E59: =D59+E21-E21*Assumptions!G62 -> 7915.5626 | F59: =E59+F21-F21*Assumptions!H62 -> 9138.6856 | G59: =F59+G21-G21*Assumptions!I62 -> 10559.757
A60: Non-controlling interests | B60: =Actuals!M28 -> 131.3 | C60: =Assumptions!$E$48 -> 131.3 | D60: =Assumptions!$E$48 -> 131.3 | E60: =Assumptions!$E$48 -> 131.3 | F60: =Assumptions!$E$48 -> 131.3 | G60: =Assumptions!$E$48 -> 131.3
A61: Total equity | B61: =SUM(B58:B60) -> 5431.36 | C61: =SUM(C58:C60) -> 6202.5222 | D61: =SUM(D58:D60) -> 7103.8386 | E61: =SUM(E58:E60) -> 8154.8326 | F61: =SUM(F58:F60) -> 9377.9556 | G61: =SUM(G58:G60) -> 10799.027
A62: LIABILITIES - NON-CURRENT
A63: Borrowings (non-current) | B63: =Actuals!M30 -> 611.34 | C63: =Actuals!$M$30 -> 611.34 | D63: =Actuals!$M$30 -> 611.34 | E63: =Actuals!$M$30 -> 611.34 | F63: =Actuals!$M$30 -> 611.34 | G63: =Actuals!$M$30 -> 611.34
A64: Lease liabilities (NC) | B64: =Actuals!M31 -> 111.49 | C64: =C6*Assumptions!E50 -> 128.49129 | D64: =D6*Assumptions!F50 -> 147.76499 | E64: =E6*Assumptions!G50 -> 169.92974 | F64: =F6*Assumptions!H50 -> 195.4192 | G64: =G6*Assumptions!I50 -> 224.73208
A65: Other financial liabilities (NC) | B65: =Actuals!M32 -> 20.63 | C65: =C6*Assumptions!E51 -> 23.504505 | D65: =D6*Assumptions!F51 -> 27.030181 | E65: =E6*Assumptions!G51 -> 31.084708 | F65: =F6*Assumptions!H51 -> 35.747414 | G65: =G6*Assumptions!I51 -> 41.109526
A66: Provisions (NC) | B66: =Actuals!M33 -> 132.09 | C66: =C6*Assumptions!E52 -> 151.9958 | D66: =D6*Assumptions!F52 -> 174.79517 | E66: =E6*Assumptions!G52 -> 201.01444 | F66: =F6*Assumptions!H52 -> 231.16661 | G66: =G6*Assumptions!I52 -> 265.8416
A67: Deferred tax liability | B67: =Actuals!M34 -> 29.38 | C67: =C6*Assumptions!E53 -> 33.68979 | D67: =D6*Assumptions!F53 -> 38.743259 | E67: =E6*Assumptions!G53 -> 44.554748 | F67: =F6*Assumptions!H53 -> 51.23796 | G67: =G6*Assumptions!I53 -> 58.923654
A68: Other non-current liabilities | B68: =Actuals!M35 -> 539.47 | C68: =C6*Assumptions!E54 -> 620.51893 | D68: =D6*Assumptions!F54 -> 713.59677 | E68: =E6*Assumptions!G54 -> 820.63629 | F68: =F6*Assumptions!H54 -> 943.73173 | G68: =G6*Assumptions!I54 -> 1085.2915
A69: Total non-current liabilities | B69: =SUM(B63:B68) -> 1444.4 | C69: =SUM(C63:C68) -> 1569.5403 | D69: =SUM(D63:D68) -> 1713.2704 | E69: =SUM(E63:E68) -> 1878.5599 | F69: =SUM(F63:F68) -> 2068.6429 | G69: =SUM(G63:G68) -> 2287.2383
A70: LIABILITIES - CURRENT
A71: Borrowings (current, incl. deficit funding) | B71: =Actuals!M37 -> 1786.15 | C71: =Assumptions!E55+MAX(0,(C46+C48+C49+C51+C52+C53+C54)-(C61+C69+C72+C73+C74+C75+C76+C77+Assumptions!E55)) -> 2138.3946 | D71: =Assumptions!F55+MAX(0,(D46+D48+D49+D51+D52+D53+D54)-(D61+D69+D72+D73+D74+D75+D76+D77+Assumptions!F55)) -> 2431.3196 | E71: =Assumptions!G55+MAX(0,(E46+E48+E49+E51+E52+E53+E54)-(E61+E69+E72+E73+E74+E75+E76+E77+Assumptions!G55)) -> 2573.7032 | F71: =Assumptions!H55+MAX(0,(F46+F48+F49+F51+F52+F53+F54)-(F61+F69+F72+F73+F74+F75+F76+F77+Assumptions!H55)) -> 2542.9644 | G71: =Assumptions!I55+MAX(0,(G46+G48+G49+G51+G52+G53+G54)-(G61+G69+G72+G73+G74+G75+G76+G77+Assumptions!I55)) -> 2313.1348
A72: Trade payables | B72: =Actuals!M38 -> 1252.09 | C72: =C6*Assumptions!E23 -> 1410.2703 | D72: =D6*Assumptions!F23 -> 1621.8108 | E72: =E6*Assumptions!G23 -> 1865.0825 | F72: =F6*Assumptions!H23 -> 2144.8448 | G72: =G6*Assumptions!I23 -> 2466.5716
A73: Lease liabilities (current) | B73: =Actuals!M39 -> 9.5 | C73: =C6*Assumptions!E56 -> 10.968769 | D73: =D6*Assumptions!F56 -> 12.614084 | E73: =E6*Assumptions!G56 -> 14.506197 | F73: =F6*Assumptions!H56 -> 16.682127 | G73: =G6*Assumptions!I56 -> 19.184446
A74: Other financial liabilities (current) | B74: =Actuals!M40 -> 333.58 | C74: =C6*Assumptions!E57 -> 383.90691 | D74: =D6*Assumptions!F57 -> 441.49295 | E74: =E6*Assumptions!G57 -> 507.7169 | F74: =F6*Assumptions!H57 -> 583.87443 | G74: =G6*Assumptions!I57 -> 671.45559
A75: Other current liabilities | B75: =Actuals!M41 -> 161.95 | C75: =C6*Assumptions!E25 -> 156.6967 | D75: =D6*Assumptions!F25 -> 180.2012 | E75: =E6*Assumptions!G25 -> 207.23139 | F75: =F6*Assumptions!H25 -> 238.31609 | G75: =G6*Assumptions!I25 -> 274.06351
A76: Provisions (current) | B76: =Actuals!M42 -> 37.89 | C76: =C6*Assumptions!E58 -> 43.875076 | D76: =D6*Assumptions!F58 -> 50.456337 | E76: =E6*Assumptions!G58 -> 58.024788 | F76: =F6*Assumptions!H58 -> 66.728506 | G76: =G6*Assumptions!I58 -> 76.737782
A77: Income tax liabilities | B77: =Actuals!M43 -> 54.27 | C77: =C6*Assumptions!E59 -> 62.67868 | D77: =D6*Assumptions!F59 -> 72.080482 | E77: =E6*Assumptions!G59 -> 82.892554 | F77: =F6*Assumptions!H59 -> 95.326437 | G77: =G6*Assumptions!I59 -> 109.6254
A78: Total current liabilities | B78: =SUM(B71:B77) -> 3635.43 | C78: =SUM(C71:C77) -> 4206.7911 | D78: =SUM(D71:D77) -> 4809.9755 | E78: =SUM(E71:E77) -> 5309.1575 | F78: =SUM(F71:F77) -> 5688.7369 | G78: =SUM(G71:G77) -> 5930.7731
A79: TOTAL EQUITY + LIABILITIES | B79: =B61+B69+B78 -> 10511.19 | C79: =C61+C69+C78 -> 11978.854 | D79: =D61+D69+D78 -> 13627.084 | E79: =E61+E69+E78 -> 15342.55 | F79: =F61+F69+F78 -> 17135.335 | G79: =G61+G69+G78 -> 19017.039
A80: BALANCE CHECK (Assets - Equity & Liabilities) | B80: =B56-B79 -> 0 | C80: =C56-C79 -> 0 | D80: =D56-D79 -> 0 | E80: =E56-E79 -> 0 | F80: =F56-F79 -> 0 | G80: =G56-G79 -> 0

Sheet Forecast 2 (Segment-based)
A3: Laurus Labs Ltd - Forecast 2: Segment based Approach | B3: t0 | C3: t1 | D3: t2 | E3: t3 | F3: t4 | G3: t5
B4: ACTUAL | C4: FORECAST
A5: Particulars | B5: FY26A | C5: FY27E | D5: FY28E | E5: FY29E | F5: FY30E | G5: FY31E
A6: SEGMENT GROWTH ASSUMPTIONS (embedded, all Analyst unless noted)
A7: CDMO - Small molecules revenue growth % | C7: 0.2 | D7: 0.2 | E7: 0.2 | F7: 0.2 | G7: 0.2 | I7: 20% a year: FY26 small-molecule CDMO grew ~38% and 9M FY26 CDMO >50%; management expects 'healthy growth' and mostly commercial supplies in FY27 (Q3 FY26 call). Normalised to 20% as the base scales.
A8: CDMO - Bio revenue growth % | C8: 0.2 | D8: 0.2 | E8: 0.2 | F8: 0.2 | G8: 0.2 | I8: 20% a year: FY26 Bio grew ~15%; new fermentation capacity being built (Q3 FY26 call: capex from 2H FY27).
A9: Affordable Medicines revenue growth % | C9: 0.1 | D9: 0.1 | E9: 0.1 | F9: 0.1 | G9: 0.1 | I9: 10% a year: FY26 grew 18% (9M FY26 generics +26%); ARV guided at Rs2,500-3,000cr (Q3 FY26 call); growth expected in FY27, more in FY28. 10% is a moderated round rate.
A11: SEGMENT REVENUE BUILD-UP
A12: CDMO - Small molecules revenue | B12: 1896 | C12: =B12*(1+C7) -> 2275.2 | D12: =C12*(1+D7) -> 2730.24 | E12: =D12*(1+E7) -> 3276.288 | F12: =E12*(1+F7) -> 3931.5456 | G12: =F12*(1+G7) -> 4717.8547 | I12: FY26A Rs1,896cr (Q4 FY26 call / AR MD&A)
A13: CDMO - Bio revenue | B13: 184 | C13: =B13*(1+C8) -> 220.8 | D13: =C13*(1+D8) -> 264.96 | E13: =D13*(1+E8) -> 317.952 | F13: =E13*(1+F8) -> 381.5424 | G13: =F13*(1+G8) -> 457.85088 | I13: FY26A Rs184cr (Q4 FY26 call / AR MD&A)
A14: CDMO revenue (total) | B14: =B12+B13 -> 2080 | C14: =C12+C13 -> 2496 | D14: =D12+D13 -> 2995.2 | E14: =E12+E13 -> 3594.24 | F14: =F12+F13 -> 4313.088 | G14: =G12+G13 -> 5175.7056
A15: Affordable Medicines revenue (residual = Total - CDMO) | B15: =Actuals!F6-B14 -> 4732.9 | C15: =B15*(1+C9) -> 5206.19 | D15: =C15*(1+D9) -> 5726.809 | E15: =D15*(1+E9) -> 6299.4899 | F15: =E15*(1+F9) -> 6929.4389 | G15: =F15*(1+G9) -> 7622.3828 | I15: FY26A = consolidated revenue less CDMO (Rs4,733cr, agrees with Q4 FY26 call)
A16: Total revenue (Forecast 2) | B16: =B14+B15 -> 6812.9 | C16: =C14+C15 -> 7702.19 | D16: =D14+D15 -> 8722.009 | E16: =E14+E15 -> 9893.7299 | F16: =F14+F15 -> 11242.527 | G16: =G14+G15 -> 12798.088
A17: CDMO % of total revenue (output of the segment growth rates; management's long-term 50% CDMO mix is an aspiration) | B17: =B14/B16 -> 0.30530317 | C17: =C14/C16 -> 0.32406368 | D17: =D14/D16 -> 0.34340712 | E17: =E14/E16 -> 0.36328463 | F17: =F14/F16 -> 0.38364044 | G17: =G14/G16 -> 0.4044124
A19: P&L (same cost-ratio logic as Forecast 1, applied to Forecast-2 revenue)
A20: Gross profit (Revenue x Gross margin%, per Assumptions) | B20: =B16-Actuals!F9-Actuals!F10-Actuals!F11 -> 4117.44 | C20: =C16*Assumptions!E8 -> 4621.314 | D20: =D16*Assumptions!F8 -> 5233.2054 | E20: =E16*Assumptions!G8 -> 5936.2379 | F20: =F16*Assumptions!H8 -> 6745.5161 | G20: =G16*Assumptions!I8 -> 7678.853
A21: Employee benefits expense | B21: =Actuals!F12 -> 895.45 | C21: =C16*Assumptions!E9 -> 1001.2847 | D21: =D16*Assumptions!F9 -> 1133.8612 | E21: =E16*Assumptions!G9 -> 1286.1849 | F21: =F16*Assumptions!H9 -> 1461.5285 | G21: =G16*Assumptions!I9 -> 1663.7515
A22: Other expenses | B22: =Actuals!F13 -> 1444.28 | C22: =C16*Assumptions!E10 -> 1617.4599 | D22: =D16*Assumptions!F10 -> 1831.6219 | E22: =E16*Assumptions!G10 -> 2077.6833 | F22: =F16*Assumptions!H10 -> 2360.9306 | G22: =G16*Assumptions!I10 -> 2687.5986
A23: EBITDA | B23: =Actuals!F15 -> 1826.09 | C23: =C20-C21-C22 -> 2002.5694 | D23: =D20-D21-D22 -> 2267.7223 | E23: =E20-E21-E22 -> 2572.3698 | F23: =F20-F21-F22 -> 2923.057 | G23: =G20-G21-G22 -> 3327.503
A24: Depreciation & amortisation | B24: =Actuals!F16 -> 480.05 | C24: =C16*Assumptions!E14 -> 577.66425 | D24: =D16*Assumptions!F14 -> 654.15067 | E24: =E16*Assumptions!G14 -> 742.02974 | F24: =F16*Assumptions!H14 -> 843.18952 | G24: =G16*Assumptions!I14 -> 959.85663
A25: EBIT | B25: =B23-B24 -> 1346.04 | C25: =C23-C24 -> 1424.9051 | D25: =D23-D24 -> 1613.5717 | E25: =E23-E24 -> 1830.34 | F25: =F23-F24 -> 2079.8675 | G25: =G23-G24 -> 2367.6464
A26: Total debt balance (held flat at FY26A) | B26: =Actuals!M30+Actuals!M37 -> 2397.49 | C26: =$B$26 -> 2397.49 | D26: =$B$26 -> 2397.49 | E26: =$B$26 -> 2397.49 | F26: =$B$26 -> 2397.49 | G26: =$B$26 -> 2397.49
A27: Interest expense | B27: =Actuals!F18 -> 170.73 | C27: =C26*Assumptions!E16 -> 167.8243 | D27: =D26*Assumptions!F16 -> 167.8243 | E27: =E26*Assumptions!G16 -> 167.8243 | F27: =F26*Assumptions!H16 -> 167.8243 | G27: =G26*Assumptions!I16 -> 167.8243
A28: Finance income (held flat at FY26A) | B28: =-Actuals!F17 -> 6.57 | C28: =-Actuals!$F$17 -> 6.57 | D28: =-Actuals!$F$17 -> 6.57 | E28: =-Actuals!$F$17 -> 6.57 | F28: =-Actuals!$F$17 -> 6.57 | G28: =-Actuals!$F$17 -> 6.57
A29: Profit before tax (EBT) | B29: =Actuals!F19 -> 1181.88 | C29: =C25-C27+C28 -> 1263.6508 | D29: =D25-D27+D28 -> 1452.3174 | E29: =E25-E27+E28 -> 1669.0857 | F29: =F25-F27+F28 -> 1918.6132 | G29: =G25-G27+G28 -> 2206.3921
A30: Tax expense | B30: =Actuals!F20 -> 292.03 | C30: =C29*Assumptions!E15 -> 318.06092 | D30: =D29*Assumptions!F15 -> 365.54828 | E30: =E29*Assumptions!G15 -> 420.10888 | F30: =F29*Assumptions!H15 -> 482.91494 | G30: =G29*Assumptions!I15 -> 555.34888
A31: Share of profit from associates/JV | B31: =Actuals!F22 -> 0.29 | C31: =Assumptions!E17 -> 0 | D31: =Assumptions!F17 -> 0 | E31: =Assumptions!G17 -> 0 | F31: =Assumptions!H17 -> 0 | G31: =Assumptions!I17 -> 0
A32: Profit before NCI | B32: =Actuals!F23 -> 890.14 | C32: =C29-C30+C31 -> 945.58993 | D32: =D29-D30+D31 -> 1086.7691 | E32: =E29-E30+E31 -> 1248.9769 | F32: =F29-F30+F31 -> 1435.6982 | G32: =G29-G30+G31 -> 1651.0432
A33: Non-controlling interests | B33: =Actuals!F24 -> 1.35 | C33: =C32*Assumptions!E18 -> 0 | D33: =D32*Assumptions!F18 -> 0 | E33: =E32*Assumptions!G18 -> 0 | F33: =F32*Assumptions!H18 -> 0 | G33: =G32*Assumptions!I18 -> 0
A34: PAT attributable to owners | B34: =Actuals!F25 -> 888.79 | C34: =C32-C33 -> 945.58993 | D34: =D32-D33 -> 1086.7691 | E34: =E32-E33 -> 1248.9769 | F34: =F32-F33 -> 1435.6982 | G34: =G32-G33 -> 1651.0432
A36: WORKING CAPITAL & CAPEX (same ratio logic as Forecast 1)
A37: Inventory | B37: =Actuals!M16 -> 2342.16 | C37: =C16*Assumptions!E21 -> 2618.7446 | D37: =D16*Assumptions!F21 -> 2965.4831 | E37: =E16*Assumptions!G21 -> 3363.8682 | F37: =F16*Assumptions!H21 -> 3822.4591 | G37: =G16*Assumptions!I21 -> 4351.35
A38: Trade receivables | B38: =Actuals!M17 -> 2155.04 | C38: =C16*Assumptions!E22 -> 2464.7008 | D38: =D16*Assumptions!F22 -> 2791.0429 | E38: =E16*Assumptions!G22 -> 3165.9936 | F38: =F16*Assumptions!H22 -> 3597.6086 | G38: =G16*Assumptions!I22 -> 4095.3883
A39: Other operating current assets | B39: =Actuals!M22 -> 214.17 | C39: =C16*Assumptions!E24 -> 231.0657 | D39: =D16*Assumptions!F24 -> 261.66027 | E39: =E16*Assumptions!G24 -> 296.8119 | F39: =F16*Assumptions!H24 -> 337.27581 | G39: =G16*Assumptions!I24 -> 383.94265
A40: Trade payables | B40: =Actuals!M38 -> 1252.09 | C40: =C16*Assumptions!E23 -> 1386.3942 | D40: =D16*Assumptions!F23 -> 1569.9616 | E40: =E16*Assumptions!G23 -> 1780.8714 | F40: =F16*Assumptions!H23 -> 2023.6548 | G40: =G16*Assumptions!I23 -> 2303.6559
A41: Other operating current liabilities | B41: =Actuals!M41 -> 161.95 | C41: =C16*Assumptions!E25 -> 154.0438 | D41: =D16*Assumptions!F25 -> 174.44018 | E41: =E16*Assumptions!G25 -> 197.8746 | F41: =F16*Assumptions!H25 -> 224.85054 | G41: =G16*Assumptions!I25 -> 255.96177
A42: Operating Working Capital (OWC) | B42: =B37+B38+B39-B40-B41 -> 3297.33 | C42: =C37+C38+C39-C40-C41 -> 3774.0731 | D42: =D37+D38+D39-D40-D41 -> 4273.7844 | E42: =E37+E38+E39-E40-E41 -> 4847.9277 | F42: =F37+F38+F39-F40-F41 -> 5508.8382 | G42: =G37+G38+G39-G40-G41 -> 6271.0633
A43: Change in OWC | C43: =C42-B42 -> 476.7431 | D43: =D42-C42 -> 499.71131 | E43: =E42-D42 -> 574.14324 | F43: =F42-E42 -> 660.91053 | G43: =G42-F42 -> 762.22513
A44: Capital expenditure | B44: =-Actuals!F29 -> 1069.95 | C44: =Assumptions!E28 -> 1200 | D44: =Assumptions!F28 -> 1200 | E44: =Assumptions!G28 -> 1200 | F44: =Assumptions!H28 -> 1200 | G44: =Assumptions!I28 -> 1200
A46: Balance Sheet | B46: t0 | C46: t1 | D46: t2 | E46: t3 | F46: t4 | G46: t5
B47: ACTUAL | C47: FORECAST
A48: Particulars | B48: FY26A | C48: FY27E | D48: FY28E | E48: FY29E | F48: FY30E | G48: FY31E
A49: Property, plant & equipment | B49: =Actuals!M6 -> 3873.23 | C49: =B49+C44-C24 -> 4495.5657 | D49: =C49+D44-D24 -> 5041.4151 | E49: =D49+E44-E24 -> 5499.3853 | F49: =E49+F44-F24 -> 5856.1958 | G49: =F49+G44-G24 -> 6096.3392
A50: Right-of-use assets | B50: =Actuals!M7 -> 232.71 | C50: =C16*Assumptions!E36 -> 263.4149 | D50: =D16*Assumptions!F36 -> 298.29271 | E50: =E16*Assumptions!G36 -> 338.36556 | F50: =F16*Assumptions!H36 -> 384.49442 | G50: =G16*Assumptions!I36 -> 437.69462
A51: Capital work-in-progress | B51: =Actuals!M8 -> 773.28 | C51: =C16*Assumptions!E37 -> 874.19857 | D51: =D16*Assumptions!F37 -> 989.94802 | E51: =E16*Assumptions!G37 -> 1122.9383 | F51: =F16*Assumptions!H37 -> 1276.0268 | G51: =G16*Assumptions!I37 -> 1452.583
A52: Goodwill | B52: =Actuals!M9 -> 246.3 | C52: =C16*Assumptions!E38 -> 278.81928 | D52: =D16*Assumptions!F38 -> 315.73673 | E52: =E16*Assumptions!G38 -> 358.15302 | F52: =F16*Assumptions!H38 -> 406.97947 | G52: =G16*Assumptions!I38 -> 463.2908
A53: Other intangible assets | B53: =Actuals!M10 -> 18.4 | C53: =C16*Assumptions!E39 -> 20.795913 | D53: =D16*Assumptions!F39 -> 23.549424 | E53: =E16*Assumptions!G39 -> 26.713071 | F53: =F16*Assumptions!H39 -> 30.354823 | G53: =G16*Assumptions!I39 -> 34.554839
A54: Investments (non-current) | B54: =Actuals!M11 -> 309.27 | C54: =C16*Assumptions!E40 -> 349.67943 | D54: =D16*Assumptions!F40 -> 395.97921 | E54: =E16*Assumptions!G40 -> 449.17534 | F54: =F16*Assumptions!H40 -> 510.41072 | G54: =G16*Assumptions!I40 -> 581.03321
A55: Other financial assets (NC) | B55: =Actuals!M12 -> 44.26 | C55: =C16*Assumptions!E41 -> 50.064235 | D55: =D16*Assumptions!F41 -> 56.693058 | E55: =E16*Assumptions!G41 -> 64.309244 | F55: =F16*Assumptions!H41 -> 73.076425 | G55: =G16*Assumptions!I41 -> 83.187574
A56: Income tax assets (NC) | B56: =Actuals!M13 -> 2.44 | C56: =C16*Assumptions!E42 -> 3.080876 | D56: =D16*Assumptions!F42 -> 3.4888036 | E56: =E16*Assumptions!G42 -> 3.957492 | F56: =F16*Assumptions!H42 -> 4.4970108 | G56: =G16*Assumptions!I42 -> 5.1192354
A57: Other non-current assets | B57: =Actuals!M14 -> 182.09 | C57: =C16*Assumptions!E43 -> 205.64847 | D57: =D16*Assumptions!F43 -> 232.87764 | E57: =E16*Assumptions!G43 -> 264.16259 | F57: =F16*Assumptions!H43 -> 300.17547 | G57: =G16*Assumptions!I43 -> 341.70896
A58: Total non-current assets | B58: =SUM(B49:B57) -> 5681.98 | C58: =SUM(C49:C57) -> 6541.2674 | D58: =SUM(D49:D57) -> 7357.9807 | E58: =SUM(E49:E57) -> 8127.16 | F58: =SUM(F49:F57) -> 8842.211 | G58: =SUM(G49:G57) -> 9495.5115
A59: ASSETS - CURRENT
A60: Inventory | B60: =Actuals!M16 -> 2342.16 | C60: =C16*Assumptions!E21 -> 2618.7446 | D60: =D16*Assumptions!F21 -> 2965.4831 | E60: =E16*Assumptions!G21 -> 3363.8682 | F60: =F16*Assumptions!H21 -> 3822.4591 | G60: =G16*Assumptions!I21 -> 4351.35
A61: Trade receivables | B61: =Actuals!M17 -> 2155.04 | C61: =C16*Assumptions!E22 -> 2464.7008 | D61: =D16*Assumptions!F22 -> 2791.0429 | E61: =E16*Assumptions!G22 -> 3165.9936 | F61: =F16*Assumptions!H22 -> 3597.6086 | G61: =G16*Assumptions!I22 -> 4095.3883
A62: Cash & cash equivalents | B62: =Actuals!M18 -> 112.66 | C62: =Actuals!N18 -> 0 | D62: =Actuals!O18 -> 0 | E62: =Actuals!P18 -> 0 | F62: =Actuals!Q18 -> 0 | G62: =Actuals!R18 -> 0
A63: Other bank balances | B63: =Actuals!M19 -> 1.04 | C63: =C16*Assumptions!E44 -> 1.540438 | D63: =D16*Assumptions!F44 -> 1.7444018 | E63: =E16*Assumptions!G44 -> 1.978746 | F63: =F16*Assumptions!H44 -> 2.2485054 | G63: =G16*Assumptions!I44 -> 2.5596177
A64: Loans (current) | B64: =Actuals!M20 -> 0.93 | C64: =C16*Assumptions!E45 -> 0.770219 | D64: =D16*Assumptions!F45 -> 0.8722009 | E64: =E16*Assumptions!G45 -> 0.98937299 | F64: =F16*Assumptions!H45 -> 1.1242527 | G64: =G16*Assumptions!I45 -> 1.2798088
A65: Other financial assets (current) | B65: =Actuals!M21 -> 3.21 | C65: =C16*Assumptions!E46 -> 3.851095 | D65: =D16*Assumptions!F46 -> 4.3610045 | E65: =E16*Assumptions!G46 -> 4.946865 | F65: =F16*Assumptions!H46 -> 5.6212634 | G65: =G16*Assumptions!I46 -> 6.3990442
A66: Other current assets | B66: =Actuals!M22 -> 214.17 | C66: =C16*Assumptions!E24 -> 231.0657 | D66: =D16*Assumptions!F24 -> 261.66027 | E66: =E16*Assumptions!G24 -> 296.8119 | F66: =F16*Assumptions!H24 -> 337.27581 | G66: =G16*Assumptions!I24 -> 383.94265
A67: Total current assets | B67: =SUM(B60:B66) -> 4829.21 | C67: =SUM(C60:C66) -> 5320.6729 | D67: =SUM(D60:D66) -> 6025.1638 | E67: =SUM(E60:E66) -> 6834.5886 | F67: =SUM(F60:F66) -> 7766.3376 | G67: =SUM(G60:G66) -> 8840.9195
A68: TOTAL ASSETS | B68: =B58+B67 -> 10511.19 | C68: =C58+C67 -> 11861.94 | D68: =D58+D67 -> 13383.144 | E68: =E58+E67 -> 14961.749 | F68: =F58+F67 -> 16608.549 | G68: =G58+G67 -> 18336.431
A69: EQUITY & LIABILITIES
A70: Equity share capital | B70: =Actuals!M25 -> 107.97 | C70: =Assumptions!$D$47 -> 107.97 | D70: =Assumptions!$D$47 -> 107.97 | E70: =Assumptions!$D$47 -> 107.97 | F70: =Assumptions!$D$47 -> 107.97 | G70: =Assumptions!$D$47 -> 107.97
A71: Other equity (retained earnings roll-forward) | B71: =Actuals!M26 -> 5192.09 | C71: =B71+C34-C34*Assumptions!E62 -> 5948.5619 | D71: =C71+D34-D34*Assumptions!F62 -> 6817.9772 | E71: =D71+E34-E34*Assumptions!G62 -> 7817.1587 | F71: =E71+F34-F34*Assumptions!H62 -> 8965.7173 | G71: =F71+G34-G34*Assumptions!I62 -> 10286.552
A72: Non-controlling interests | B72: =Actuals!M28 -> 131.3 | C72: =Assumptions!$E$48 -> 131.3 | D72: =Assumptions!F48 -> 131.3 | E72: =Assumptions!G48 -> 131.3 | F72: =Assumptions!H48 -> 131.3 | G72: =Assumptions!I48 -> 131.3
A73: Total equity | B73: =SUM(B70:B72) -> 5431.36 | C73: =SUM(C70:C72) -> 6187.8319 | D73: =SUM(D70:D72) -> 7057.2472 | E73: =SUM(E70:E72) -> 8056.4287 | F73: =SUM(F70:F72) -> 9204.9873 | G73: =SUM(G70:G72) -> 10525.822
A74: LIABILITIES - NON-CURRENT
A75: Borrowings (non-current) | B75: =Actuals!M30 -> 611.34 | C75: =Actuals!$M$30 -> 611.34 | D75: =Actuals!$M$30 -> 611.34 | E75: =Actuals!$M$30 -> 611.34 | F75: =Actuals!$M$30 -> 611.34 | G75: =Actuals!$M$30 -> 611.34
A76: Lease liabilities (NC) | B76: =Actuals!M31 -> 111.49 | C76: =C16*Assumptions!E50 -> 126.31592 | D76: =D16*Assumptions!F50 -> 143.04095 | E76: =E16*Assumptions!G50 -> 162.25717 | F76: =F16*Assumptions!H50 -> 184.37744 | G76: =G16*Assumptions!I50 -> 209.88865
A77: Other financial liabilities (NC) | B77: =Actuals!M32 -> 20.63 | C77: =C16*Assumptions!E51 -> 23.10657 | D77: =D16*Assumptions!F51 -> 26.166027 | E77: =E16*Assumptions!G51 -> 29.68119 | F77: =F16*Assumptions!H51 -> 33.727581 | G77: =G16*Assumptions!I51 -> 38.394265
A78: Provisions (NC) | B78: =Actuals!M33 -> 132.09 | C78: =C16*Assumptions!E52 -> 149.42249 | D78: =D16*Assumptions!F52 -> 169.20697 | E78: =E16*Assumptions!G52 -> 191.93836 | F78: =F16*Assumptions!H52 -> 218.10502 | G78: =G16*Assumptions!I52 -> 248.28291
A79: Deferred tax liability | B79: =Actuals!M34 -> 29.38 | C79: =C16*Assumptions!E53 -> 33.119417 | D79: =D16*Assumptions!F53 -> 37.504639 | E79: =E16*Assumptions!G53 -> 42.543039 | F79: =F16*Assumptions!H53 -> 48.342866 | G79: =G16*Assumptions!I53 -> 55.03178
A80: Other non-current liabilities | B80: =Actuals!M35 -> 539.47 | C80: =C16*Assumptions!E54 -> 610.01345 | D80: =D16*Assumptions!F54 -> 690.78311 | E80: =E16*Assumptions!G54 -> 783.58341 | F80: =F16*Assumptions!H54 -> 890.40813 | G80: =G16*Assumptions!I54 -> 1013.6086
A81: Total non-current liabilities | B81: =SUM(B75:B80) -> 1444.4 | C81: =SUM(C75:C80) -> 1553.3178 | D81: =SUM(D75:D80) -> 1678.0417 | E81: =SUM(E75:E80) -> 1821.3432 | F81: =SUM(F75:F80) -> 1986.301 | G81: =SUM(G75:G80) -> 2176.5462
A82: LIABILITIES - CURRENT
A83: Borrowings (current, incl. deficit funding) | B83: =Actuals!M37 -> 1786.15 | C83: =Assumptions!E55+MAX(0,(C58+C60+C61+C63+C64+C65+C66)-(C73+C81+C84+C85+C86+C87+C88+C89+Assumptions!E55)) -> 2087.4123 | D83: =Assumptions!F55+MAX(0,(D58+D60+D61+D63+D64+D65+D66)-(D73+D81+D84+D85+D86+D87+D88+D89+Assumptions!F55)) -> 2345.2452 | E83: =Assumptions!G55+MAX(0,(E58+E60+E61+E63+E64+E65+E66)-(E73+E81+E84+E85+E86+E87+E88+E89+Assumptions!G55)) -> 2472.0321 | F83: =Assumptions!H55+MAX(0,(F58+F60+F61+F63+F64+F65+F66)-(F73+F81+F84+F85+F86+F87+F88+F89+Assumptions!H55)) -> 2449.2331 | G83: =Assumptions!I55+MAX(0,(G58+G60+G61+G63+G64+G65+G66)-(G73+G81+G84+G85+G86+G87+G88+G89+Assumptions!I55)) -> 2255.3675
A84: Trade payables | B84: =Actuals!M38 -> 1252.09 | C84: =C16*Assumptions!E23 -> 1386.3942 | D84: =D16*Assumptions!F23 -> 1569.9616 | E84: =E16*Assumptions!G23 -> 1780.8714 | F84: =F16*Assumptions!H23 -> 2023.6548 | G84: =G16*Assumptions!I23 -> 2303.6559
A85: Lease liabilities (current) | B85: =Actuals!M39 -> 9.5 | C85: =C16*Assumptions!E56 -> 10.783066 | D85: =D16*Assumptions!F56 -> 12.210813 | E85: =E16*Assumptions!G56 -> 13.851222 | F85: =F16*Assumptions!H56 -> 15.739538 | G85: =G16*Assumptions!I56 -> 17.917324
A86: Other financial liabilities (current) | B86: =Actuals!M40 -> 333.58 | C86: =C16*Assumptions!E57 -> 377.40731 | D86: =D16*Assumptions!F57 -> 427.37844 | E86: =E16*Assumptions!G57 -> 484.79277 | F86: =F16*Assumptions!H57 -> 550.88382 | G86: =G16*Assumptions!I57 -> 627.10633
A87: Other current liabilities | B87: =Actuals!M41 -> 161.95 | C87: =C16*Assumptions!E25 -> 154.0438 | D87: =D16*Assumptions!F25 -> 174.44018 | E87: =E16*Assumptions!G25 -> 197.8746 | F87: =F16*Assumptions!H25 -> 224.85054 | G87: =G16*Assumptions!I25 -> 255.96177
A88: Provisions (current) | B88: =Actuals!M42 -> 37.89 | C88: =C16*Assumptions!E58 -> 43.132264 | D88: =D16*Assumptions!F58 -> 48.84325 | E88: =E16*Assumptions!G58 -> 55.404887 | F88: =F16*Assumptions!H58 -> 62.958151 | G88: =G16*Assumptions!I58 -> 71.669295
A89: Income tax liabilities | B89: =Actuals!M43 -> 54.27 | C89: =C16*Assumptions!E59 -> 61.61752 | D89: =D16*Assumptions!F59 -> 69.776072 | E89: =E16*Assumptions!G59 -> 79.149839 | F89: =F16*Assumptions!H59 -> 89.940215 | G89: =G16*Assumptions!I59 -> 102.38471
A90: Total current liabilities | B90: =SUM(B83:B89) -> 3635.43 | C90: =SUM(C83:C89) -> 4120.7905 | D90: =SUM(D83:D89) -> 4647.8556 | E90: =SUM(E83:E89) -> 5083.9767 | F90: =SUM(F83:F89) -> 5417.2602 | G90: =SUM(G83:G89) -> 5634.0629
A91: TOTAL EQUITY + LIABILITIES | B91: =B73+B81+B90 -> 10511.19 | C91: =C73+C81+C90 -> 11861.94 | D91: =D73+D81+D90 -> 13383.144 | E91: =E73+E81+E90 -> 14961.749 | F91: =F73+F81+F90 -> 16608.549 | G91: =G73+G81+G90 -> 18336.431
A92: BALANCE CHECK (Assets - Equity & Liabilities) | B92: =B68-B91 -> 0 | C92: =C68-C91 -> 0 | D92: =D68-D91 -> 0 | E92: =E68-E91 -> 0 | F92: =F68-F91 -> 0 | G92: =G68-G91 -> 0

Sheet DCF-FCFF
A3: SCENARIO 1: Revenue Growth / Operating Margin (Forecast 1) | B3: t0 | C3: t1 | D3: t2 | E3: t3 | F3: t4 | G3: t5 | J3: EV-to-equity bridge components (FY26A, Rs Cr, consolidated) - single source for DCF, EP and Relative Valuation
B4: ACTUAL | C4: FORECAST | J4: Borrowings - non-current | K4: =Actuals!M30 -> 611.34
A5: Particulars | B5: FY26A | C5: FY27E | D5: FY28E | E5: FY29E | F5: FY30E | G5: FY31E | J5: Borrowings - current | K5: =Actuals!M37 -> 1786.15
A6: EBIT | C6: ='Forecast 1 (Growth-Margin)'!C12 -> 1449.4445 | D6: ='Forecast 1 (Growth-Margin)'!D12 -> 1666.8611 | E6: ='Forecast 1 (Growth-Margin)'!E12 -> 1916.8903 | F6: ='Forecast 1 (Growth-Margin)'!F12 -> 2204.4239 | G6: ='Forecast 1 (Growth-Margin)'!G12 -> 2535.0874 | J6: Lease liabilities - non-current (debt-like) | K6: =Actuals!M31 -> 111.49
A7: Tax rate | C7: =Assumptions!E15 -> 0.2517 | D7: =Assumptions!F15 -> 0.2517 | E7: =Assumptions!G15 -> 0.2517 | F7: =Assumptions!H15 -> 0.2517 | G7: =Assumptions!I15 -> 0.2517 | J7: Lease liabilities - current (debt-like) | K7: =Actuals!M39 -> 9.5
A8: NOPAT = EBIT x (1-Tax) | C8: =C6*(1-C7) -> 1084.6193 | D8: =D6*(1-D7) -> 1247.3122 | E8: =E6*(1-E7) -> 1434.409 | F8: =F6*(1-F7) -> 1649.5704 | G8: =G6*(1-G7) -> 1897.0059 | J8: Total debt & debt-like obligations | K8: =SUM(K4:K7) -> 2518.48
A9: + Depreciation & amortisation | C9: ='Forecast 1 (Growth-Margin)'!C11 -> 587.61262 | D9: ='Forecast 1 (Growth-Margin)'!D11 -> 675.75452 | E9: ='Forecast 1 (Growth-Margin)'!E11 -> 777.1177 | F9: ='Forecast 1 (Growth-Margin)'!F11 -> 893.68535 | G9: ='Forecast 1 (Growth-Margin)'!G11 -> 1027.7382 | J9: Cash & cash equivalents | K9: =Actuals!M18 -> 112.66
A10: - Capital expenditure | C10: =-'Forecast 1 (Growth-Margin)'!C32 -> -1200 | D10: =-'Forecast 1 (Growth-Margin)'!D32 -> -1200 | E10: =-'Forecast 1 (Growth-Margin)'!E32 -> -1200 | F10: =-'Forecast 1 (Growth-Margin)'!F32 -> -1200 | G10: =-'Forecast 1 (Growth-Margin)'!G32 -> -1200 | J10: Other bank balances | K10: =Actuals!M19 -> 1.04
A11: - Change in Operating Working Capital | C11: =-'Forecast 1 (Growth-Margin)'!C31 -> -541.73915 | D11: =-'Forecast 1 (Growth-Margin)'!D31 -> -575.86037 | E11: =-'Forecast 1 (Growth-Margin)'!E31 -> -662.23943 | F11: =-'Forecast 1 (Growth-Margin)'!F31 -> -761.57534 | G11: =-'Forecast 1 (Growth-Margin)'!G31 -> -875.81164 | J11: Non-operating investments (non-current investments) | K11: =Actuals!M11 -> 309.27
A12: FCFF | C12: =C8+C9+C10+C11 -> -69.507224 | D12: =D8+D9+D10+D11 -> 147.20634 | E12: =E8+E9+E10+E11 -> 349.28729 | F12: =F8+F9+F10+F11 -> 581.68039 | G12: =G8+G9+G10+G11 -> 848.93245 | J12: Total cash & non-operating assets | K12: =SUM(K9:K11) -> 422.97
A13: Discount factor @ WACC | C13: =1/(1+'Cost of Capital'!$B$23)^1 -> 0.87721382 | D13: =1/(1+'Cost of Capital'!$B$23)^2 -> 0.76950409 | E13: =1/(1+'Cost of Capital'!$B$23)^3 -> 0.67501962 | F13: =1/(1+'Cost of Capital'!$B$23)^4 -> 0.59213654 | G13: =1/(1+'Cost of Capital'!$B$23)^5 -> 0.51943036 | J13: Non-controlling interests | K13: =Actuals!M28 -> 131.3
A14: PV of FCFF | C14: =C12*C13 -> -60.972698 | D14: =D12*D13 -> 113.27588 | E14: =E12*E13 -> 235.77578 | F14: =F12*F13 -> 344.43421 | G14: =G12*G13 -> 440.96128
A15: Closing invested capital FY31E (from Economic Profit tab) | B15: ='Economic Profit'!G14 -> 12982.188
A16: Sum of PV of explicit-period FCFF | B16: =SUM(C14:G14) -> 1073.4745
A17: Terminal value = [NOPAT(FY31E) x (1+g) - g x Invested Capital(FY31E)] / (WACC - g) | B17: =(G8*(1+'Cost of Capital'!$B$25)-'Cost of Capital'!$B$25*B15)/('Cost of Capital'!$B$23-'Cost of Capital'!$B$25) -> 14539.924
A18: PV of Terminal value | B18: =B17*G13 -> 7552.4781
A19: Enterprise Value | B19: =B16+B18 -> 8625.9526
A20: Less: Debt & lease liabilities (FY26A, see components at right) | B20: =-$K$8 -> -2518.48
A21: Add: Cash + other bank balances + non-operating investments (FY26A) | B21: =$K$12 -> 422.97
A22: Less: Non-controlling interests (FY26A) | B22: =-$K$13 -> -131.3
A23: Equity Value attributable to owners | B23: =B19+B20+B21+B22 -> 6399.1426
A24: Diluted shares outstanding (Crore) | B24: =Assumptions!D29 -> 53.985658
A25: Intrinsic Value per Share (Rs) - Scenario 1 | B25: =B23/B24 -> 118.53412
A27: SCENARIO 2: Segment / Capacity-Aligned (Forecast 2) | B27: t0 | C27: t1 | D27: t2 | E27: t3 | F27: t4 | G27: t5
B28: ACTUAL | C28: FORECAST
A29: Particulars | B29: FY26A | C29: FY27E | D29: FY28E | E29: FY29E | F29: FY30E | G29: FY31E
A30: EBIT | C30: ='Forecast 2 (Segment-based)'!C25 -> 1424.9051 | D30: ='Forecast 2 (Segment-based)'!D25 -> 1613.5717 | E30: ='Forecast 2 (Segment-based)'!E25 -> 1830.34 | F30: ='Forecast 2 (Segment-based)'!F25 -> 2079.8675 | G30: ='Forecast 2 (Segment-based)'!G25 -> 2367.6464
A31: Tax rate | C31: =Assumptions!E15 -> 0.2517 | D31: =Assumptions!F15 -> 0.2517 | E31: =Assumptions!G15 -> 0.2517 | F31: =Assumptions!H15 -> 0.2517 | G31: =Assumptions!I15 -> 0.2517
A32: NOPAT = EBIT x (1-Tax) | C32: =C30*(1-C31) -> 1066.2565 | D32: =D30*(1-D31) -> 1207.4357 | E32: =E30*(1-E31) -> 1369.6434 | F32: =F30*(1-F31) -> 1556.3648 | G32: =G30*(1-G31) -> 1771.7098
A33: + Depreciation & amortisation | C33: ='Forecast 2 (Segment-based)'!C24 -> 577.66425 | D33: ='Forecast 2 (Segment-based)'!D24 -> 654.15067 | E33: ='Forecast 2 (Segment-based)'!E24 -> 742.02974 | F33: ='Forecast 2 (Segment-based)'!F24 -> 843.18952 | G33: ='Forecast 2 (Segment-based)'!G24 -> 959.85663
A34: - Capital expenditure | C34: =-'Forecast 2 (Segment-based)'!C44 -> -1200 | D34: =-'Forecast 2 (Segment-based)'!D44 -> -1200 | E34: =-'Forecast 2 (Segment-based)'!E44 -> -1200 | F34: =-'Forecast 2 (Segment-based)'!F44 -> -1200 | G34: =-'Forecast 2 (Segment-based)'!G44 -> -1200
A35: - Change in Operating Working Capital | C35: =-'Forecast 2 (Segment-based)'!C43 -> -476.7431 | D35: =-'Forecast 2 (Segment-based)'!D43 -> -499.71131 | E35: =-'Forecast 2 (Segment-based)'!E43 -> -574.14324 | F35: =-'Forecast 2 (Segment-based)'!F43 -> -660.91053 | G35: =-'Forecast 2 (Segment-based)'!G43 -> -762.22513
A36: FCFF | C36: =C32+C33+C34+C35 -> -32.822326 | D36: =D32+D33+D34+D35 -> 161.87504 | E36: =E32+E33+E34+E35 -> 337.52995 | F36: =F32+F33+F34+F35 -> 538.64382 | G36: =G32+G33+G34+G35 -> 769.34126
A37: Discount factor @ WACC | C37: =1/(1+'Cost of Capital'!$B$23)^1 -> 0.87721382 | D37: =1/(1+'Cost of Capital'!$B$23)^2 -> 0.76950409 | E37: =1/(1+'Cost of Capital'!$B$23)^3 -> 0.67501962 | F37: =1/(1+'Cost of Capital'!$B$23)^4 -> 0.59213654 | G37: =1/(1+'Cost of Capital'!$B$23)^5 -> 0.51943036
A38: PV of FCFF | C38: =C36*C37 -> -28.792198 | D38: =D36*D37 -> 124.56351 | E38: =E36*E37 -> 227.83934 | F38: =F36*F37 -> 318.95069 | G38: =G36*G37 -> 399.61921
A39: Closing invested capital FY31E (opening IC + capex - D&A + change in OWC) | B39: ='Economic Profit'!B6+SUM('Forecast 2 (Segment-based)'!C44:G44)-SUM('Forecast 2 (Segment-based)'!C24:G24)+SUM('Forecast 2 (Segment-based)'!C43:G43) -> 12723.712
A40: Sum of PV of explicit-period FCFF | B40: =SUM(C38:G38) -> 1042.1805
A41: Terminal value = [NOPAT(FY31E) x (1+g) - g x Invested Capital(FY31E)] / (WACC - g) | B41: =(G32*(1+'Cost of Capital'!$B$25)-'Cost of Capital'!$B$25*B39)/('Cost of Capital'!$B$23-'Cost of Capital'!$B$25) -> 13339.909
A42: PV of Terminal value | B42: =B41*G37 -> 6929.1538
A43: Enterprise Value | B43: =B40+B42 -> 7971.3344
A44: Less: Debt & lease liabilities (FY26A, see components at right) | B44: =-$K$8 -> -2518.48
A45: Add: Cash + other bank balances + non-operating investments (FY26A) | B45: =$K$12 -> 422.97
A46: Less: Non-controlling interests (FY26A) | B46: =-$K$13 -> -131.3
A47: Equity Value attributable to owners | B47: =B43+B44+B45+B46 -> 5744.5244
A48: Shares outstanding (Crore) | B48: =Assumptions!D29 -> 53.985658
A49: Intrinsic Value per Share (Rs) - Scenario 2 | B49: =B47/B48 -> 106.40834
A52: SENSITIVITY: Intrinsic value per share (Rs), Scenario 1 - WACC (rows) vs terminal growth (columns)
A54: WACC \ g | B54: 0.03 | C54: 0.035 | D54: 0.04 | E54: 0.045 | F54: 0.05
A55: 0.12 | B55: =((C12/(1+0.12)^1+D12/(1+0.12)^2+E12/(1+0.12)^3+F12/(1+0.12)^4+G12/(1+0.12)^5+((G8*(1+0.03)-0.03*$B$15)/(0.12-0.03))/(1+0.12)^5)+$B$20+$B$21+$B$22)/$B$24 -> 162.85679 | C55: =((C12/(1+0.12)^1+D12/(1+0.12)^2+E12/(1+0.12)^3+F12/(1+0.12)^4+G12/(1+0.12)^5+((G8*(1+0.035)-0.035*$B$15)/(0.12-0.035))/(1+0.12)^5)+$B$20+$B$21+$B$22)/$B$24 -> 166.75045 | D55: =((C12/(1+0.12)^1+D12/(1+0.12)^2+E12/(1+0.12)^3+F12/(1+0.12)^4+G12/(1+0.12)^5+((G8*(1+0.04)-0.04*$B$15)/(0.12-0.04))/(1+0.12)^5)+$B$20+$B$21+$B$22)/$B$24 -> 171.13082 | E55: =((C12/(1+0.12)^1+D12/(1+0.12)^2+E12/(1+0.12)^3+F12/(1+0.12)^4+G12/(1+0.12)^5+((G8*(1+0.045)-0.045*$B$15)/(0.12-0.045))/(1+0.12)^5)+$B$20+$B$21+$B$22)/$B$24 -> 176.09523 | F55: =((C12/(1+0.12)^1+D12/(1+0.12)^2+E12/(1+0.12)^3+F12/(1+0.12)^4+G12/(1+0.12)^5+((G8*(1+0.05)-0.05*$B$15)/(0.12-0.05))/(1+0.12)^5)+$B$20+$B$21+$B$22)/$B$24 -> 181.76884
A56: 0.13 | B56: =((C12/(1+0.13)^1+D12/(1+0.13)^2+E12/(1+0.13)^3+F12/(1+0.13)^4+G12/(1+0.13)^5+((G8*(1+0.03)-0.03*$B$15)/(0.13-0.03))/(1+0.13)^5)+$B$20+$B$21+$B$22)/$B$24 -> 136.66166 | C56: =((C12/(1+0.13)^1+D12/(1+0.13)^2+E12/(1+0.13)^3+F12/(1+0.13)^4+G12/(1+0.13)^5+((G8*(1+0.035)-0.035*$B$15)/(0.13-0.035))/(1+0.13)^5)+$B$20+$B$21+$B$22)/$B$24 -> 139.0742 | D56: =((C12/(1+0.13)^1+D12/(1+0.13)^2+E12/(1+0.13)^3+F12/(1+0.13)^4+G12/(1+0.13)^5+((G8*(1+0.04)-0.04*$B$15)/(0.13-0.04))/(1+0.13)^5)+$B$20+$B$21+$B$22)/$B$24 -> 141.75481 | E56: =((C12/(1+0.13)^1+D12/(1+0.13)^2+E12/(1+0.13)^3+F12/(1+0.13)^4+G12/(1+0.13)^5+((G8*(1+0.045)-0.045*$B$15)/(0.13-0.045))/(1+0.13)^5)+$B$20+$B$21+$B$22)/$B$24 -> 144.75079 | F56: =((C12/(1+0.13)^1+D12/(1+0.13)^2+E12/(1+0.13)^3+F12/(1+0.13)^4+G12/(1+0.13)^5+((G8*(1+0.05)-0.05*$B$15)/(0.13-0.05))/(1+0.13)^5)+$B$20+$B$21+$B$22)/$B$24 -> 148.12126
A57: 0.14 | B57: =((C12/(1+0.14)^1+D12/(1+0.14)^2+E12/(1+0.14)^3+F12/(1+0.14)^4+G12/(1+0.14)^5+((G8*(1+0.03)-0.03*$B$15)/(0.14-0.03))/(1+0.14)^5)+$B$20+$B$21+$B$22)/$B$24 -> 115.45962 | C57: =((C12/(1+0.14)^1+D12/(1+0.14)^2+E12/(1+0.14)^3+F12/(1+0.14)^4+G12/(1+0.14)^5+((G8*(1+0.035)-0.035*$B$15)/(0.14-0.035))/(1+0.14)^5)+$B$20+$B$21+$B$22)/$B$24 -> 116.89678 | D57: =((C12/(1+0.14)^1+D12/(1+0.14)^2+E12/(1+0.14)^3+F12/(1+0.14)^4+G12/(1+0.14)^5+((G8*(1+0.04)-0.04*$B$15)/(0.14-0.04))/(1+0.14)^5)+$B$20+$B$21+$B$22)/$B$24 -> 118.47766 | E57: =((C12/(1+0.14)^1+D12/(1+0.14)^2+E12/(1+0.14)^3+F12/(1+0.14)^4+G12/(1+0.14)^5+((G8*(1+0.045)-0.045*$B$15)/(0.14-0.045))/(1+0.14)^5)+$B$20+$B$21+$B$22)/$B$24 -> 120.22495 | F57: =((C12/(1+0.14)^1+D12/(1+0.14)^2+E12/(1+0.14)^3+F12/(1+0.14)^4+G12/(1+0.14)^5+((G8*(1+0.05)-0.05*$B$15)/(0.14-0.05))/(1+0.14)^5)+$B$20+$B$21+$B$22)/$B$24 -> 122.16638
A58: 0.15 | B58: =((C12/(1+0.15)^1+D12/(1+0.15)^2+E12/(1+0.15)^3+F12/(1+0.15)^4+G12/(1+0.15)^5+((G8*(1+0.03)-0.03*$B$15)/(0.15-0.03))/(1+0.15)^5)+$B$20+$B$21+$B$22)/$B$24 -> 97.99091 | C58: =((C12/(1+0.15)^1+D12/(1+0.15)^2+E12/(1+0.15)^3+F12/(1+0.15)^4+G12/(1+0.15)^5+((G8*(1+0.035)-0.035*$B$15)/(0.15-0.035))/(1+0.15)^5)+$B$20+$B$21+$B$22)/$B$24 -> 98.772472 | D58: =((C12/(1+0.15)^1+D12/(1+0.15)^2+E12/(1+0.15)^3+F12/(1+0.15)^4+G12/(1+0.15)^5+((G8*(1+0.04)-0.04*$B$15)/(0.15-0.04))/(1+0.15)^5)+$B$20+$B$21+$B$22)/$B$24 -> 99.625085 | E58: =((C12/(1+0.15)^1+D12/(1+0.15)^2+E12/(1+0.15)^3+F12/(1+0.15)^4+G12/(1+0.15)^5+((G8*(1+0.045)-0.045*$B$15)/(0.15-0.045))/(1+0.15)^5)+$B$20+$B$21+$B$22)/$B$24 -> 100.5589 | F58: =((C12/(1+0.15)^1+D12/(1+0.15)^2+E12/(1+0.15)^3+F12/(1+0.15)^4+G12/(1+0.15)^5+((G8*(1+0.05)-0.05*$B$15)/(0.15-0.05))/(1+0.15)^5)+$B$20+$B$21+$B$22)/$B$24 -> 101.5861
A59: 0.16 | B59: =((C12/(1+0.16)^1+D12/(1+0.16)^2+E12/(1+0.16)^3+F12/(1+0.16)^4+G12/(1+0.16)^5+((G8*(1+0.03)-0.03*$B$15)/(0.16-0.03))/(1+0.16)^5)+$B$20+$B$21+$B$22)/$B$24 -> 83.384039 | C59: =((C12/(1+0.16)^1+D12/(1+0.16)^2+E12/(1+0.16)^3+F12/(1+0.16)^4+G12/(1+0.16)^5+((G8*(1+0.035)-0.035*$B$15)/(0.16-0.035))/(1+0.16)^5)+$B$20+$B$21+$B$22)/$B$24 -> 83.718836 | D59: =((C12/(1+0.16)^1+D12/(1+0.16)^2+E12/(1+0.16)^3+F12/(1+0.16)^4+G12/(1+0.16)^5+((G8*(1+0.04)-0.04*$B$15)/(0.16-0.04))/(1+0.16)^5)+$B$20+$B$21+$B$22)/$B$24 -> 84.081533 | E59: =((C12/(1+0.16)^1+D12/(1+0.16)^2+E12/(1+0.16)^3+F12/(1+0.16)^4+G12/(1+0.16)^5+((G8*(1+0.045)-0.045*$B$15)/(0.16-0.045))/(1+0.16)^5)+$B$20+$B$21+$B$22)/$B$24 -> 84.475769 | F59: =((C12/(1+0.16)^1+D12/(1+0.16)^2+E12/(1+0.16)^3+F12/(1+0.16)^4+G12/(1+0.16)^5+((G8*(1+0.05)-0.05*$B$15)/(0.16-0.05))/(1+0.16)^5)+$B$20+$B$21+$B$22)/$B$24 -> 84.905845

Sheet Economic Profit
A3: ECONOMIC PROFIT BUILD (Scenario 1 basis) | B3: t0 | C3: t1 | D3: t2 | E3: t3 | F3: t4 | G3: t5
B4: ACTUAL | C4: FORECAST
A5: Particulars | B5: FY26A | C5: FY27E | D5: FY28E | E5: FY29E | F5: FY30E | G5: FY31E
A6: Opening Invested Capital (FY26A) | B6: =Actuals!M29+'DCF-FCFF'!K8-'DCF-FCFF'!K12 -> 7526.87
A7: NOPAT (= EBIT x (1-Tax), from DCF Scenario 1) | C7: ='DCF-FCFF'!C8 -> 1084.6193 | D7: ='DCF-FCFF'!D8 -> 1247.3122 | E7: ='DCF-FCFF'!E8 -> 1434.409 | F7: ='DCF-FCFF'!F8 -> 1649.5704 | G7: ='DCF-FCFF'!G8 -> 1897.0059
A8: Opening Invested Capital | C8: =$B$6 -> 7526.87 | D8: =C14 -> 8680.9965 | E8: =D14 -> 9781.1024 | F8: =E14 -> 10866.224 | G8: =F14 -> 11934.114
A9: Less: Capital charge (WACC x Opening IC) | C9: =C8*'Cost of Capital'!$B$23 -> 1053.558 | D9: =D8*'Cost of Capital'!$B$23 -> 1215.1044 | E9: =E8*'Cost of Capital'!$B$23 -> 1369.0894 | F9: =F8*'Cost of Capital'!$B$23 -> 1520.9771 | G9: =G8*'Cost of Capital'!$B$23 -> 1670.4528
A10: Economic Profit (EVA) | C10: =C7-C9 -> 31.061341 | D10: =D7-D9 -> 32.207778 | E10: =E7-E9 -> 65.31958 | F10: =F7-F9 -> 128.59328 | G10: =G7-G9 -> 226.55316
A11: Discount factor @ WACC | C11: =1/(1+'Cost of Capital'!$B$23)^1 -> 0.87721382 | D11: =1/(1+'Cost of Capital'!$B$23)^2 -> 0.76950409 | E11: =1/(1+'Cost of Capital'!$B$23)^3 -> 0.67501962 | F11: =1/(1+'Cost of Capital'!$B$23)^4 -> 0.59213654 | G11: =1/(1+'Cost of Capital'!$B$23)^5 -> 0.51943036
A12: PV of Economic Profit | C12: =C10*C11 -> 27.247437 | D12: =D10*D11 -> 24.784017 | E12: =E10*E11 -> 44.091998 | F12: =F10*F11 -> 76.144779 | G12: =G10*G11 -> 117.67859
A13: Net new investment (Capex - Depreciation + Change in OWC) | C13: ='Forecast 1 (Growth-Margin)'!C32-'Forecast 1 (Growth-Margin)'!C11+'Forecast 1 (Growth-Margin)'!C31 -> 1154.1265 | D13: ='Forecast 1 (Growth-Margin)'!D32-'Forecast 1 (Growth-Margin)'!D11+'Forecast 1 (Growth-Margin)'!D31 -> 1100.1059 | E13: ='Forecast 1 (Growth-Margin)'!E32-'Forecast 1 (Growth-Margin)'!E11+'Forecast 1 (Growth-Margin)'!E31 -> 1085.1217 | F13: ='Forecast 1 (Growth-Margin)'!F32-'Forecast 1 (Growth-Margin)'!F11+'Forecast 1 (Growth-Margin)'!F31 -> 1067.89 | G13: ='Forecast 1 (Growth-Margin)'!G32-'Forecast 1 (Growth-Margin)'!G11+'Forecast 1 (Growth-Margin)'!G31 -> 1048.0735
A14: Closing Invested Capital | C14: =C8+C13 -> 8680.9965 | D14: =D8+D13 -> 9781.1024 | E14: =E8+E13 -> 10866.224 | F14: =F8+F13 -> 11934.114 | G14: =G8+G13 -> 12982.188
A16: Sum of PV of explicit-period Economic Profit | B16: =SUM(C12:G12) -> 289.94682
A17: Terminal EP value = [NOPAT(FY31E) x (1+g) - WACC x Invested Capital(FY31E)] / (WACC - g) | B17: =(G7*(1+'Cost of Capital'!$B$25)-'Cost of Capital'!$B$23*G14)/('Cost of Capital'!$B$23-'Cost of Capital'!$B$25) -> 1557.7368
A18: PV of Terminal Economic Profit | B18: =B17*G11 -> 809.13576
A19: Firm Value (EP method) = Opening IC + PV(explicit EP) + PV(Terminal EP) | B19: =B6+B16+B18 -> 8625.9526
A21: RECONCILIATION CHECK (proves the EP model is built correctly)
A22: Enterprise Value per FCFF DCF (Scenario 1, DCF-FCFF tab) | B22: ='DCF-FCFF'!B19 -> 8625.9526
A23: Enterprise Value per Economic Profit method (above) | B23: =B19 -> 8625.9526
A24: Difference (must be ~0) | B24: =B19-B22 -> 0
A25: Difference as % of FCFF EV | B25: =B24/B22 -> 0
A27: EQUITY VALUE PER SHARE (EP method)
A29: Enterprise Value (EP method) | B29: =B19 -> 8625.9526
A30: Less: Debt & lease liabilities (FY26A) | B30: =-'DCF-FCFF'!K8 -> -2518.48
A31: Add: Cash + other bank balances + non-operating investments (FY26A) | B31: ='DCF-FCFF'!K12 -> 422.97
A32: Less: Non-controlling interests (FY26A) | B32: =-'DCF-FCFF'!K13 -> -131.3
A33: Equity Value attributable to owners | B33: =B19+B30+B31+B32 -> 6399.1426
A34: Diluted shares outstanding (Crore) | B34: =Assumptions!D29 -> 53.985658
A35: Intrinsic Value per Share (Rs) - Economic Profit method | B35: =B33/B34 -> 118.53412
A37: SENSITIVITY: value per share (Rs), Economic Profit method - WACC (rows) vs terminal growth (columns)
A39: WACC \ g | B39: 0.03 | C39: 0.035 | D39: 0.04 | E39: 0.045 | F39: 0.05
A40: 0.12 | B40: =($B$6+(C7-0.12*C8)/(1+0.12)^1+(D7-0.12*D8)/(1+0.12)^2+(E7-0.12*E8)/(1+0.12)^3+(F7-0.12*F8)/(1+0.12)^4+(G7-0.12*G8)/(1+0.12)^5+((G7*(1+0.03)-0.12*G14)/(0.12-0.03))/(1+0.12)^5+$B$30+$B$31+$B$32)/$B$34 -> 162.85679 | C40: =($B$6+(C7-0.12*C8)/(1+0.12)^1+(D7-0.12*D8)/(1+0.12)^2+(E7-0.12*E8)/(1+0.12)^3+(F7-0.12*F8)/(1+0.12)^4+(G7-0.12*G8)/(1+0.12)^5+((G7*(1+0.035)-0.12*G14)/(0.12-0.035))/(1+0.12)^5+$B$30+$B$31+$B$32)/$B$34 -> 166.75045 | D40: =($B$6+(C7-0.12*C8)/(1+0.12)^1+(D7-0.12*D8)/(1+0.12)^2+(E7-0.12*E8)/(1+0.12)^3+(F7-0.12*F8)/(1+0.12)^4+(G7-0.12*G8)/(1+0.12)^5+((G7*(1+0.04)-0.12*G14)/(0.12-0.04))/(1+0.12)^5+$B$30+$B$31+$B$32)/$B$34 -> 171.13082 | E40: =($B$6+(C7-0.12*C8)/(1+0.12)^1+(D7-0.12*D8)/(1+0.12)^2+(E7-0.12*E8)/(1+0.12)^3+(F7-0.12*F8)/(1+0.12)^4+(G7-0.12*G8)/(1+0.12)^5+((G7*(1+0.045)-0.12*G14)/(0.12-0.045))/(1+0.12)^5+$B$30+$B$31+$B$32)/$B$34 -> 176.09523 | F40: =($B$6+(C7-0.12*C8)/(1+0.12)^1+(D7-0.12*D8)/(1+0.12)^2+(E7-0.12*E8)/(1+0.12)^3+(F7-0.12*F8)/(1+0.12)^4+(G7-0.12*G8)/(1+0.12)^5+((G7*(1+0.05)-0.12*G14)/(0.12-0.05))/(1+0.12)^5+$B$30+$B$31+$B$32)/$B$34 -> 181.76884
A41: 0.13 | B41: =($B$6+(C7-0.13*C8)/(1+0.13)^1+(D7-0.13*D8)/(1+0.13)^2+(E7-0.13*E8)/(1+0.13)^3+(F7-0.13*F8)/(1+0.13)^4+(G7-0.13*G8)/(1+0.13)^5+((G7*(1+0.03)-0.13*G14)/(0.13-0.03))/(1+0.13)^5+$B$30+$B$31+$B$32)/$B$34 -> 136.66166 | C41: =($B$6+(C7-0.13*C8)/(1+0.13)^1+(D7-0.13*D8)/(1+0.13)^2+(E7-0.13*E8)/(1+0.13)^3+(F7-0.13*F8)/(1+0.13)^4+(G7-0.13*G8)/(1+0.13)^5+((G7*(1+0.035)-0.13*G14)/(0.13-0.035))/(1+0.13)^5+$B$30+$B$31+$B$32)/$B$34 -> 139.0742 | D41: =($B$6+(C7-0.13*C8)/(1+0.13)^1+(D7-0.13*D8)/(1+0.13)^2+(E7-0.13*E8)/(1+0.13)^3+(F7-0.13*F8)/(1+0.13)^4+(G7-0.13*G8)/(1+0.13)^5+((G7*(1+0.04)-0.13*G14)/(0.13-0.04))/(1+0.13)^5+$B$30+$B$31+$B$32)/$B$34 -> 141.75481 | E41: =($B$6+(C7-0.13*C8)/(1+0.13)^1+(D7-0.13*D8)/(1+0.13)^2+(E7-0.13*E8)/(1+0.13)^3+(F7-0.13*F8)/(1+0.13)^4+(G7-0.13*G8)/(1+0.13)^5+((G7*(1+0.045)-0.13*G14)/(0.13-0.045))/(1+0.13)^5+$B$30+$B$31+$B$32)/$B$34 -> 144.75079 | F41: =($B$6+(C7-0.13*C8)/(1+0.13)^1+(D7-0.13*D8)/(1+0.13)^2+(E7-0.13*E8)/(1+0.13)^3+(F7-0.13*F8)/(1+0.13)^4+(G7-0.13*G8)/(1+0.13)^5+((G7*(1+0.05)-0.13*G14)/(0.13-0.05))/(1+0.13)^5+$B$30+$B$31+$B$32)/$B$34 -> 148.12126
A42: 0.14 | B42: =($B$6+(C7-0.14*C8)/(1+0.14)^1+(D7-0.14*D8)/(1+0.14)^2+(E7-0.14*E8)/(1+0.14)^3+(F7-0.14*F8)/(1+0.14)^4+(G7-0.14*G8)/(1+0.14)^5+((G7*(1+0.03)-0.14*G14)/(0.14-0.03))/(1+0.14)^5+$B$30+$B$31+$B$32)/$B$34 -> 115.45962 | C42: =($B$6+(C7-0.14*C8)/(1+0.14)^1+(D7-0.14*D8)/(1+0.14)^2+(E7-0.14*E8)/(1+0.14)^3+(F7-0.14*F8)/(1+0.14)^4+(G7-0.14*G8)/(1+0.14)^5+((G7*(1+0.035)-0.14*G14)/(0.14-0.035))/(1+0.14)^5+$B$30+$B$31+$B$32)/$B$34 -> 116.89678 | D42: =($B$6+(C7-0.14*C8)/(1+0.14)^1+(D7-0.14*D8)/(1+0.14)^2+(E7-0.14*E8)/(1+0.14)^3+(F7-0.14*F8)/(1+0.14)^4+(G7-0.14*G8)/(1+0.14)^5+((G7*(1+0.04)-0.14*G14)/(0.14-0.04))/(1+0.14)^5+$B$30+$B$31+$B$32)/$B$34 -> 118.47766 | E42: =($B$6+(C7-0.14*C8)/(1+0.14)^1+(D7-0.14*D8)/(1+0.14)^2+(E7-0.14*E8)/(1+0.14)^3+(F7-0.14*F8)/(1+0.14)^4+(G7-0.14*G8)/(1+0.14)^5+((G7*(1+0.045)-0.14*G14)/(0.14-0.045))/(1+0.14)^5+$B$30+$B$31+$B$32)/$B$34 -> 120.22495 | F42: =($B$6+(C7-0.14*C8)/(1+0.14)^1+(D7-0.14*D8)/(1+0.14)^2+(E7-0.14*E8)/(1+0.14)^3+(F7-0.14*F8)/(1+0.14)^4+(G7-0.14*G8)/(1+0.14)^5+((G7*(1+0.05)-0.14*G14)/(0.14-0.05))/(1+0.14)^5+$B$30+$B$31+$B$32)/$B$34 -> 122.16638
A43: 0.15 | B43: =($B$6+(C7-0.15*C8)/(1+0.15)^1+(D7-0.15*D8)/(1+0.15)^2+(E7-0.15*E8)/(1+0.15)^3+(F7-0.15*F8)/(1+0.15)^4+(G7-0.15*G8)/(1+0.15)^5+((G7*(1+0.03)-0.15*G14)/(0.15-0.03))/(1+0.15)^5+$B$30+$B$31+$B$32)/$B$34 -> 97.99091 | C43: =($B$6+(C7-0.15*C8)/(1+0.15)^1+(D7-0.15*D8)/(1+0.15)^2+(E7-0.15*E8)/(1+0.15)^3+(F7-0.15*F8)/(1+0.15)^4+(G7-0.15*G8)/(1+0.15)^5+((G7*(1+0.035)-0.15*G14)/(0.15-0.035))/(1+0.15)^5+$B$30+$B$31+$B$32)/$B$34 -> 98.772472 | D43: =($B$6+(C7-0.15*C8)/(1+0.15)^1+(D7-0.15*D8)/(1+0.15)^2+(E7-0.15*E8)/(1+0.15)^3+(F7-0.15*F8)/(1+0.15)^4+(G7-0.15*G8)/(1+0.15)^5+((G7*(1+0.04)-0.15*G14)/(0.15-0.04))/(1+0.15)^5+$B$30+$B$31+$B$32)/$B$34 -> 99.625085 | E43: =($B$6+(C7-0.15*C8)/(1+0.15)^1+(D7-0.15*D8)/(1+0.15)^2+(E7-0.15*E8)/(1+0.15)^3+(F7-0.15*F8)/(1+0.15)^4+(G7-0.15*G8)/(1+0.15)^5+((G7*(1+0.045)-0.15*G14)/(0.15-0.045))/(1+0.15)^5+$B$30+$B$31+$B$32)/$B$34 -> 100.5589 | F43: =($B$6+(C7-0.15*C8)/(1+0.15)^1+(D7-0.15*D8)/(1+0.15)^2+(E7-0.15*E8)/(1+0.15)^3+(F7-0.15*F8)/(1+0.15)^4+(G7-0.15*G8)/(1+0.15)^5+((G7*(1+0.05)-0.15*G14)/(0.15-0.05))/(1+0.15)^5+$B$30+$B$31+$B$32)/$B$34 -> 101.5861
A44: 0.16 | B44: =($B$6+(C7-0.16*C8)/(1+0.16)^1+(D7-0.16*D8)/(1+0.16)^2+(E7-0.16*E8)/(1+0.16)^3+(F7-0.16*F8)/(1+0.16)^4+(G7-0.16*G8)/(1+0.16)^5+((G7*(1+0.03)-0.16*G14)/(0.16-0.03))/(1+0.16)^5+$B$30+$B$31+$B$32)/$B$34 -> 83.384039 | C44: =($B$6+(C7-0.16*C8)/(1+0.16)^1+(D7-0.16*D8)/(1+0.16)^2+(E7-0.16*E8)/(1+0.16)^3+(F7-0.16*F8)/(1+0.16)^4+(G7-0.16*G8)/(1+0.16)^5+((G7*(1+0.035)-0.16*G14)/(0.16-0.035))/(1+0.16)^5+$B$30+$B$31+$B$32)/$B$34 -> 83.718836 | D44: =($B$6+(C7-0.16*C8)/(1+0.16)^1+(D7-0.16*D8)/(1+0.16)^2+(E7-0.16*E8)/(1+0.16)^3+(F7-0.16*F8)/(1+0.16)^4+(G7-0.16*G8)/(1+0.16)^5+((G7*(1+0.04)-0.16*G14)/(0.16-0.04))/(1+0.16)^5+$B$30+$B$31+$B$32)/$B$34 -> 84.081533 | E44: =($B$6+(C7-0.16*C8)/(1+0.16)^1+(D7-0.16*D8)/(1+0.16)^2+(E7-0.16*E8)/(1+0.16)^3+(F7-0.16*F8)/(1+0.16)^4+(G7-0.16*G8)/(1+0.16)^5+((G7*(1+0.045)-0.16*G14)/(0.16-0.045))/(1+0.16)^5+$B$30+$B$31+$B$32)/$B$34 -> 84.475769 | F44: =($B$6+(C7-0.16*C8)/(1+0.16)^1+(D7-0.16*D8)/(1+0.16)^2+(E7-0.16*E8)/(1+0.16)^3+(F7-0.16*F8)/(1+0.16)^4+(G7-0.16*G8)/(1+0.16)^5+((G7*(1+0.05)-0.16*G14)/(0.16-0.05))/(1+0.16)^5+$B$30+$B$31+$B$32)/$B$34 -> 84.905845

Sheet Relative Valuation
A3: Laurus Labs Ltd - Relative (Comparable Company) Valuation
A4: Peer | B4: P/E (31-Mar-2026) | C4: ROE % | D4: ROCE % | E4: EV/EBITDA (31-Mar-2026) | F4: Why this peer
A5: Divi's Laboratories | B5: 85.71 | C5: 0.1653 | D5: 0.2197 | E5: 40.7 | F5: Closest peer: API/custom-synthesis (CDMO-like) model, similar return profile
A6: Torrent Pharmaceuticals | B6: 85.04 | C6: 0.2743 | D6: 0.1519 | E6: 36.4 | F6: Large Indian pharma, premium-rated growth compounder
A7: Sun Pharmaceutical | B7: 35.18 | C7: 0.1595 | D7: 0.2053 | E7: 21.4 | F7: India's largest pharma; benchmark for large-cap sector multiple
A8: Zydus Lifesciences | B8: 24.67 | C8: 0.2125 | D8: 0.2114 | E8: 11.3 | F8: Diversified generics/API player with similar scale and ROCE
A9: Cipla | B9: 31.59 | C9: 0.116 | D9: 0.1549 | E9: 14.1 | F9: Large generics/ARV-linked player (Cipla also in HIV therapy)
A10: Mankind Pharma | B10: 47.94 | C10: 0.1314 | D10: 0.1353 | E10: 23.7 | F10: Large-cap Indian pharma of comparable market value
A11: Laurus Labs Ltd | B11: ='Cost of Capital'!B17/'Relative Valuation'!B21 -> 60.364567 | C11: 0.08 | D11: 0.177 | E11: =(53606+Actuals!O42-Actuals!M18)/Actuals!F15 -> 30.673088 | F11: Market cap = Rs 53606 (Laurus Labs’ official FY2025–26 Integrated Annual Report)
A13: Median of 6 peer companies | B13: =MEDIAN(B5:B10) -> 41.56 | C13: =MEDIAN(C5:C10) -> 0.1624 | D13: =MEDIAN(D5:D10) -> 0.1801 | E13: =MEDIAN(E5:E10) -> 22.55
A14: P/E - 25th percentile | B14: =QUARTILE(B5:B10,1) -> 32.4875
A15: P/E - 75th percentile | B15: =QUARTILE(B5:B10,3) -> 75.765
A17: EV/EBITDA - 25th percentile | B17: =QUARTILE(E5:E10,1) -> 15.925
A18: EV/EBITDA - 75th percentile | B18: =QUARTILE(E5:E10,3) -> 33.225
A20: P/E METHOD
A21: Laurus FY26A diluted EPS (Rs) = PAT attributable to owners / diluted weighted-average shares | B21: =Actuals!F25/Assumptions!D30 -> 16.445078
A22: Implied value per share (median P/E x EPS) | B22: =B13*B21 -> 683.45743
A23: Low (25th percentile P/E) | B23: =B14*B21 -> 534.25947
A24: High (75th percentile P/E) | B24: =B15*B21 -> 1245.9613
A26: EV/EBITDA METHOD
A27: Laurus FY26A EBITDA (Rs Cr, consolidated) | B27: =Actuals!F15 -> 1826.09
A28: Less: Debt & lease liabilities (FY26A) | B28: =-'DCF-FCFF'!K8 -> -2518.48
A29: Add: Cash + other bank balances + non-operating investments (FY26A) | B29: ='DCF-FCFF'!K12 -> 422.97
A30: Less: Non-controlling interests (FY26A) | B30: =-'DCF-FCFF'!K13 -> -131.3
A31: Shares outstanding, period-end 31-Mar-2026 (Crore) - for value per share | B31: =Assumptions!D29 -> 53.985658
A32: Implied value per share (median EV/EBITDA x EBITDA, less net debt) | B32: =(E13*$B$27+$B$28+$B$29+$B$30)/$B$31 -> 721.51606
A33: Low (25th percentile) | B33: =(B17*$B$27+$B$28+$B$29+$B$30)/$B$31 -> 497.42236
A34: High (75th percentile) | B34: =(B18*$B$27+$B$28+$B$29+$B$30)/$B$31 -> 1082.6029

Sheet Football Field
A1: Laurus Labs Ltd - Football Field (Rs per share, valuation date 31-Mar-2026)
A4: Method | B4: Low | C4: Point estimate | D4: High | E4: Range | F4: Source | H4: CMP Line Helper
A5: DCF-FCFF | B5: =MIN('DCF-FCFF'!B55:F59) -> 83.384039 | C5: =AVERAGE('DCF-FCFF'!B25,'DCF-FCFF'!B49) -> 112.47123 | D5: =MAX('DCF-FCFF'!B55:F59) -> 181.76884 | E5: =D5-B5 -> 98.384806 | F5: DCF sensitivity grid (DCF-FCFF tab); point = Scenario 1 & 2 average | H5: CMP X (₹) | I5: =$B$8 -> 83.384039
A6: Market Comparables ( P/E method) | B6: ='Relative Valuation'!B23 -> 534.25947 | C6: ='Relative Valuation'!B22 -> 683.45743 | D6: ='Relative Valuation'!B24 -> 1245.9613 | E6: =D6-B6 -> 711.70186 | H6: Start Y | I6: 0
A7: EV/EBITDA method | B7: ='Relative Valuation'!B33 -> 497.42236 | C7: ='Relative Valuation'!B32 -> 721.51606 | D7: ='Relative Valuation'!B34 -> 1082.6029 | E7: =D7-B7 -> 585.18055 | H7: End Y | I7: 4
A8: Economic Profit | B8: =MIN('Economic Profit'!B40:F44) -> 83.384039 | C8: ='Economic Profit'!B35 -> 118.53412 | D8: =MAX('Economic Profit'!B40:F44) -> 181.76884 | E8: =D8-B8 -> 98.384806 | F8: Economic Profit sensitivity grid (Economic Profit tab)
A9: CMP (Rs, 30-Mar-2026 close; last trading day before valuation date) | B9: ='Cost of Capital'!B17 -> 992.7 | H9: CMP marker | I9: ₹992.70
A12: VALUATION SUMMARY
A13: Method | B13: Value per share (Rs) | C13: Weight | D13: Contribution
A14: DCF-FCFF | B14: =C5 -> 112.47123 | C14: 0.333 | D14: =B14*C14 -> 37.45292
A15: Market Comparables ( P/E method) | B15: =C6 -> 683.45743 | C15: 0.333 | D15: =B15*C15 -> 227.59133
A16: Economic Profit | B16: =C8 -> 118.53412 | C16: 0.333 | D16: =B16*C16 -> 39.471863
A17: Equal-weighted reference value per share (3 methods) | C17: 1 | D17: =SUM(D14:D16) -> 304.51611
